[
  {
    "name": "﻿Архангай",
    "value": 680,
    "taxonomy": "city_mulaware",
    "code1": null,
    "code2": "01"
  },
  {
    "name": "Salta",
    "value": 569,
    "taxonomy": "city_mulaware",
    "code1": "AR_A",
    "code2": "A"
  },
  {
    "name": "Hokkaido",
    "value": 212,
    "taxonomy": "city_mulaware",
    "code1": null,
    "code2": "01"
  },
  {
    "name": "Aveiro",
    "value": 248,
    "taxonomy": "city_mulaware",
    "code1": null,
    "code2": "01"
  },
  {
    "name": "Баян-Өлгий",
    "value": 681,
    "taxonomy": "city_mulaware",
    "code1": null,
    "code2": "02"
  },
  {
    "name": "Aomori",
    "value": 203,
    "taxonomy": "city_mulaware",
    "code1": null,
    "code2": "02"
  },
  {
    "name": "Beja",
    "value": 249,
    "taxonomy": "city_mulaware",
    "code1": null,
    "code2": "02"
  },
  {
    "name": "Iwate",
    "value": 216,
    "taxonomy": "city_mulaware",
    "code1": null,
    "code2": "03"
  },
  {
    "name": "Braga",
    "value": 250,
    "taxonomy": "city_mulaware",
    "code1": null,
    "code2": "03"
  },
  {
    "name": "Баянхонгор",
    "value": 682,
    "taxonomy": "city_mulaware",
    "code1": null,
    "code2": "03"
  },
  {
    "name": "Bragança",
    "value": 251,
    "taxonomy": "city_mulaware",
    "code1": null,
    "code2": "04"
  },
  {
    "name": "Miyagi",
    "value": 224,
    "taxonomy": "city_mulaware",
    "code1": null,
    "code2": "04"
  },
  {
    "name": "Булган",
    "value": 683,
    "taxonomy": "city_mulaware",
    "code1": null,
    "code2": "04"
  },
  {
    "name": "Castelo Branco",
    "value": 252,
    "taxonomy": "city_mulaware",
    "code1": null,
    "code2": "05"
  },
  {
    "name": "Говь-Алтай",
    "value": 684,
    "taxonomy": "city_mulaware",
    "code1": null,
    "code2": "05"
  },
  {
    "name": "Akita",
    "value": 202,
    "taxonomy": "city_mulaware",
    "code1": null,
    "code2": "05"
  },
  {
    "name": "Дорноговь",
    "value": 685,
    "taxonomy": "city_mulaware",
    "code1": null,
    "code2": "06"
  },
  {
    "name": "Coimbra",
    "value": 253,
    "taxonomy": "city_mulaware",
    "code1": null,
    "code2": "06"
  },
  {
    "name": "Yamagata",
    "value": 245,
    "taxonomy": "city_mulaware",
    "code1": null,
    "code2": "06"
  },
  {
    "name": "Fukushima",
    "value": 208,
    "taxonomy": "city_mulaware",
    "code1": null,
    "code2": "07"
  },
  {
    "name": "Évora",
    "value": 254,
    "taxonomy": "city_mulaware",
    "code1": null,
    "code2": "07"
  },
  {
    "name": "Дорнод",
    "value": 686,
    "taxonomy": "city_mulaware",
    "code1": null,
    "code2": "07"
  },
  {
    "name": "Дундговь",
    "value": 687,
    "taxonomy": "city_mulaware",
    "code1": null,
    "code2": "08"
  },
  {
    "name": "Ibaraki",
    "value": 214,
    "taxonomy": "city_mulaware",
    "code1": null,
    "code2": "08"
  },
  {
    "name": "Faro",
    "value": 255,
    "taxonomy": "city_mulaware",
    "code1": null,
    "code2": "08"
  },
  {
    "name": "Guarda",
    "value": 256,
    "taxonomy": "city_mulaware",
    "code1": null,
    "code2": "09"
  },
  {
    "name": "Tochigi",
    "value": 239,
    "taxonomy": "city_mulaware",
    "code1": null,
    "code2": "09"
  },
  {
    "name": "Завхан",
    "value": 688,
    "taxonomy": "city_mulaware",
    "code1": null,
    "code2": "09"
  },
  {
    "name": "Leiria",
    "value": 257,
    "taxonomy": "city_mulaware",
    "code1": null,
    "code2": "10"
  },
  {
    "name": "Gunma",
    "value": 210,
    "taxonomy": "city_mulaware",
    "code1": null,
    "code2": "10"
  },
  {
    "name": "Өвөрхангай",
    "value": 689,
    "taxonomy": "city_mulaware",
    "code1": null,
    "code2": "10"
  },
  {
    "name": "Өмнөговь",
    "value": 690,
    "taxonomy": "city_mulaware",
    "code1": null,
    "code2": "11"
  },
  {
    "name": "Lisboa",
    "value": 258,
    "taxonomy": "city_mulaware",
    "code1": null,
    "code2": "11"
  },
  {
    "name": "Saitama",
    "value": 235,
    "taxonomy": "city_mulaware",
    "code1": null,
    "code2": "11"
  },
  {
    "name": "Сүхбаатар",
    "value": 691,
    "taxonomy": "city_mulaware",
    "code1": null,
    "code2": "12"
  },
  {
    "name": "Chiba",
    "value": 204,
    "taxonomy": "city_mulaware",
    "code1": null,
    "code2": "12"
  },
  {
    "name": "Portalegre",
    "value": 259,
    "taxonomy": "city_mulaware",
    "code1": null,
    "code2": "12"
  },
  {
    "name": "Tokyo",
    "value": 243,
    "taxonomy": "city_mulaware",
    "code1": null,
    "code2": "13"
  },
  {
    "name": "Сэлэнгэ",
    "value": 692,
    "taxonomy": "city_mulaware",
    "code1": null,
    "code2": "13"
  },
  {
    "name": "Porto",
    "value": 260,
    "taxonomy": "city_mulaware",
    "code1": null,
    "code2": "13"
  },
  {
    "name": "Kanagawa",
    "value": 219,
    "taxonomy": "city_mulaware",
    "code1": null,
    "code2": "14"
  },
  {
    "name": "Santarém",
    "value": 261,
    "taxonomy": "city_mulaware",
    "code1": null,
    "code2": "14"
  },
  {
    "name": "Төв",
    "value": 693,
    "taxonomy": "city_mulaware",
    "code1": null,
    "code2": "14"
  },
  {
    "name": "Setúbal",
    "value": 262,
    "taxonomy": "city_mulaware",
    "code1": null,
    "code2": "15"
  },
  {
    "name": "Увс",
    "value": 694,
    "taxonomy": "city_mulaware",
    "code1": null,
    "code2": "15"
  },
  {
    "name": "Niigata",
    "value": 229,
    "taxonomy": "city_mulaware",
    "code1": null,
    "code2": "15"
  },
  {
    "name": "Viana do Castelo",
    "value": 263,
    "taxonomy": "city_mulaware",
    "code1": null,
    "code2": "16"
  },
  {
    "name": "Toyama",
    "value": 242,
    "taxonomy": "city_mulaware",
    "code1": null,
    "code2": "16"
  },
  {
    "name": "Ховд",
    "value": 695,
    "taxonomy": "city_mulaware",
    "code1": null,
    "code2": "16"
  },
  {
    "name": "Vila Real",
    "value": 264,
    "taxonomy": "city_mulaware",
    "code1": null,
    "code2": "17"
  },
  {
    "name": "Ishikawa",
    "value": 215,
    "taxonomy": "city_mulaware",
    "code1": null,
    "code2": "17"
  },
  {
    "name": "Хөвсгөл",
    "value": 696,
    "taxonomy": "city_mulaware",
    "code1": null,
    "code2": "17"
  },
  {
    "name": "Viseu",
    "value": 265,
    "taxonomy": "city_mulaware",
    "code1": null,
    "code2": "18"
  },
  {
    "name": "Хэнтий",
    "value": 697,
    "taxonomy": "city_mulaware",
    "code1": null,
    "code2": "18"
  },
  {
    "name": "Fukui",
    "value": 206,
    "taxonomy": "city_mulaware",
    "code1": null,
    "code2": "18"
  },
  {
    "name": "Yamanashi",
    "value": 247,
    "taxonomy": "city_mulaware",
    "code1": null,
    "code2": "19"
  },
  {
    "name": "Дархан-Уул",
    "value": 698,
    "taxonomy": "city_mulaware",
    "code1": null,
    "code2": "19"
  },
  {
    "name": "Açores",
    "value": 266,
    "taxonomy": "city_mulaware",
    "code1": null,
    "code2": "20"
  },
  {
    "name": "Nagano",
    "value": 226,
    "taxonomy": "city_mulaware",
    "code1": null,
    "code2": "20"
  },
  {
    "name": "Орхон",
    "value": 699,
    "taxonomy": "city_mulaware",
    "code1": null,
    "code2": "20"
  },
  {
    "name": "Gifu",
    "value": 209,
    "taxonomy": "city_mulaware",
    "code1": null,
    "code2": "21"
  },
  {
    "name": "Shizuoka",
    "value": 238,
    "taxonomy": "city_mulaware",
    "code1": null,
    "code2": "22"
  },
  {
    "name": "УБ - Хан Уул",
    "value": 700,
    "taxonomy": "city_mulaware",
    "code1": null,
    "code2": "23"
  },
  {
    "name": "Aichi",
    "value": 201,
    "taxonomy": "city_mulaware",
    "code1": null,
    "code2": "23"
  },
  {
    "name": "УБ - Баянзүрх",
    "value": 701,
    "taxonomy": "city_mulaware",
    "code1": null,
    "code2": "24"
  },
  {
    "name": "Mie",
    "value": 223,
    "taxonomy": "city_mulaware",
    "code1": null,
    "code2": "24"
  },
  {
    "name": "Shiga",
    "value": 236,
    "taxonomy": "city_mulaware",
    "code1": null,
    "code2": "25"
  },
  {
    "name": "УБ - Сүхбаатар",
    "value": 702,
    "taxonomy": "city_mulaware",
    "code1": null,
    "code2": "25"
  },
  {
    "name": "УБ - Баянгол",
    "value": 703,
    "taxonomy": "city_mulaware",
    "code1": null,
    "code2": "26"
  },
  {
    "name": "Kyoto",
    "value": 222,
    "taxonomy": "city_mulaware",
    "code1": null,
    "code2": "26"
  },
  {
    "name": "Osaka",
    "value": 233,
    "taxonomy": "city_mulaware",
    "code1": null,
    "code2": "27"
  },
  {
    "name": "УБ - Багануур",
    "value": 704,
    "taxonomy": "city_mulaware",
    "code1": null,
    "code2": "27"
  },
  {
    "name": "УБ - Багахангай",
    "value": 705,
    "taxonomy": "city_mulaware",
    "code1": null,
    "code2": "28"
  },
  {
    "name": "Hyogo",
    "value": 213,
    "taxonomy": "city_mulaware",
    "code1": null,
    "code2": "28"
  },
  {
    "name": "Nara",
    "value": 228,
    "taxonomy": "city_mulaware",
    "code1": null,
    "code2": "29"
  },
  {
    "name": "УБ - Налайх",
    "value": 706,
    "taxonomy": "city_mulaware",
    "code1": null,
    "code2": "29"
  },
  {
    "name": "Madeira",
    "value": 267,
    "taxonomy": "city_mulaware",
    "code1": null,
    "code2": "30"
  },
  {
    "name": "Wakayama",
    "value": 244,
    "taxonomy": "city_mulaware",
    "code1": null,
    "code2": "30"
  },
  {
    "name": "Tottori",
    "value": 241,
    "taxonomy": "city_mulaware",
    "code1": null,
    "code2": "31"
  },
  {
    "name": "Говьсүмбэр",
    "value": 707,
    "taxonomy": "city_mulaware",
    "code1": null,
    "code2": "32"
  },
  {
    "name": "Shimane",
    "value": 237,
    "taxonomy": "city_mulaware",
    "code1": null,
    "code2": "32"
  },
  {
    "name": "Okayama",
    "value": 231,
    "taxonomy": "city_mulaware",
    "code1": null,
    "code2": "33"
  },
  {
    "name": "Hiroshima",
    "value": 211,
    "taxonomy": "city_mulaware",
    "code1": null,
    "code2": "34"
  },
  {
    "name": "УБ - Сонгино Хайрхан",
    "value": 708,
    "taxonomy": "city_mulaware",
    "code1": null,
    "code2": "34"
  },
  {
    "name": "Yamaguchi",
    "value": 246,
    "taxonomy": "city_mulaware",
    "code1": null,
    "code2": "35"
  },
  {
    "name": "УБ - Чингэлтэй",
    "value": 709,
    "taxonomy": "city_mulaware",
    "code1": null,
    "code2": "35"
  },
  {
    "name": "Tokushima",
    "value": 240,
    "taxonomy": "city_mulaware",
    "code1": null,
    "code2": "36"
  },
  {
    "name": "Kagawa",
    "value": 217,
    "taxonomy": "city_mulaware",
    "code1": null,
    "code2": "37"
  },
  {
    "name": "Ehime",
    "value": 205,
    "taxonomy": "city_mulaware",
    "code1": null,
    "code2": "38"
  },
  {
    "name": "Kochi",
    "value": 220,
    "taxonomy": "city_mulaware",
    "code1": null,
    "code2": "39"
  },
  {
    "name": "Fukuoka",
    "value": 207,
    "taxonomy": "city_mulaware",
    "code1": null,
    "code2": "40"
  },
  {
    "name": "Saga",
    "value": 234,
    "taxonomy": "city_mulaware",
    "code1": null,
    "code2": "41"
  },
  {
    "name": "Nagasaki",
    "value": 227,
    "taxonomy": "city_mulaware",
    "code1": null,
    "code2": "42"
  },
  {
    "name": "Kumamoto",
    "value": 221,
    "taxonomy": "city_mulaware",
    "code1": null,
    "code2": "43"
  },
  {
    "name": "Oita",
    "value": 230,
    "taxonomy": "city_mulaware",
    "code1": null,
    "code2": "44"
  },
  {
    "name": "Miyazaki",
    "value": 225,
    "taxonomy": "city_mulaware",
    "code1": null,
    "code2": "45"
  },
  {
    "name": "Kagoshima",
    "value": 218,
    "taxonomy": "city_mulaware",
    "code1": null,
    "code2": "46"
  },
  {
    "name": "Okinawa",
    "value": 232,
    "taxonomy": "city_mulaware",
    "code1": null,
    "code2": "47"
  },
  {
    "name": "Alacant (Alicante)",
    "value": 420,
    "taxonomy": "city_mulaware",
    "code1": null,
    "code2": "A"
  },
  {
    "name": "Armed Forces Americas",
    "value": 68,
    "taxonomy": "city_mulaware",
    "code1": null,
    "code2": "AA"
  },
  {
    "name": "Albacete",
    "value": 419,
    "taxonomy": "city_mulaware",
    "code1": null,
    "code2": "AB"
  },
  {
    "name": "Alberta",
    "value": 533,
    "taxonomy": "city_mulaware",
    "code1": null,
    "code2": "AB"
  },
  {
    "name": "Aceh",
    "value": 613,
    "taxonomy": "city_mulaware",
    "code1": null,
    "code2": "AC"
  },
  {
    "name": "Acre",
    "value": 71,
    "taxonomy": "city_mulaware",
    "code1": null,
    "code2": "AC"
  },
  {
    "name": "Australian Capital Territory",
    "value": 1,
    "taxonomy": "city_mulaware",
    "code1": null,
    "code2": "ACT"
  },
  {
    "name": "Republic of Adygeya",
    "value": 98,
    "taxonomy": "city_mulaware",
    "code1": null,
    "code2": "AD"
  },
  {
    "name": "Armed Forces Europe",
    "value": 69,
    "taxonomy": "city_mulaware",
    "code1": null,
    "code2": "AE"
  },
  {
    "name": "Agrigento",
    "value": 306,
    "taxonomy": "city_mulaware",
    "code1": null,
    "code2": "AG"
  },
  {
    "name": "Aguascalientes",
    "value": 485,
    "taxonomy": "city_mulaware",
    "code1": null,
    "code2": "AGU"
  },
  {
    "name": "Ajman",
    "value": 547,
    "taxonomy": "city_mulaware",
    "code1": null,
    "code2": "AJ"
  },
  {
    "name": "Alaska",
    "value": 10,
    "taxonomy": "city_mulaware",
    "code1": null,
    "code2": "AK"
  },
  {
    "name": "Alabama",
    "value": 9,
    "taxonomy": "city_mulaware",
    "code1": null,
    "code2": "AL"
  },
  {
    "name": "Alessandria",
    "value": 307,
    "taxonomy": "city_mulaware",
    "code1": null,
    "code2": "AL"
  },
  {
    "name": "Almería",
    "value": 421,
    "taxonomy": "city_mulaware",
    "code1": null,
    "code2": "AL"
  },
  {
    "name": "Alagoas",
    "value": 72,
    "taxonomy": "city_mulaware",
    "code1": null,
    "code2": "AL"
  },
  {
    "name": "Altai Republic",
    "value": 99,
    "taxonomy": "city_mulaware",
    "code1": null,
    "code2": "AL"
  },
  {
    "name": "Altai Krai",
    "value": 100,
    "taxonomy": "city_mulaware",
    "code1": null,
    "code2": "ALT"
  },
  {
    "name": "Alexandria",
    "value": 273,
    "taxonomy": "city_mulaware",
    "code1": null,
    "code2": "ALX"
  },
  {
    "name": "Amazonas",
    "value": 74,
    "taxonomy": "city_mulaware",
    "code1": null,
    "code2": "AM"
  },
  {
    "name": "Amazonas",
    "value": 675,
    "taxonomy": "city_mulaware",
    "code1": null,
    "code2": "AMA"
  },
  {
    "name": "Amur Oblast",
    "value": 101,
    "taxonomy": "city_mulaware",
    "code1": null,
    "code2": "AMU"
  },
  {
    "name": "Andaman and Nicobar",
    "value": 577,
    "taxonomy": "city_mulaware",
    "code1": null,
    "code2": "AN"
  },
  {
    "name": "Ancona",
    "value": 308,
    "taxonomy": "city_mulaware",
    "code1": null,
    "code2": "AN"
  },
  {
    "name": "Antioquia",
    "value": 647,
    "taxonomy": "city_mulaware",
    "code1": null,
    "code2": "ANT"
  },
  {
    "name": "Aosta",
    "value": 309,
    "taxonomy": "city_mulaware",
    "code1": null,
    "code2": "AO"
  },
  {
    "name": "Ascoli Piceno",
    "value": 311,
    "taxonomy": "city_mulaware",
    "code1": null,
    "code2": "AP"
  },
  {
    "name": "Amapá",
    "value": 73,
    "taxonomy": "city_mulaware",
    "code1": null,
    "code2": "AP"
  },
  {
    "name": "Armed Forces Pacific",
    "value": 70,
    "taxonomy": "city_mulaware",
    "code1": null,
    "code2": "AP"
  },
  {
    "name": "Andhra Pradesh",
    "value": 578,
    "taxonomy": "city_mulaware",
    "code1": null,
    "code2": "AP"
  },
  {
    "name": "L'Aquila",
    "value": 350,
    "taxonomy": "city_mulaware",
    "code1": null,
    "code2": "AQ"
  },
  {
    "name": "Arkansas",
    "value": 12,
    "taxonomy": "city_mulaware",
    "code1": null,
    "code2": "AR"
  },
  {
    "name": "Arunachal Pradesh",
    "value": 579,
    "taxonomy": "city_mulaware",
    "code1": null,
    "code2": "AR"
  },
  {
    "name": "Arezzo",
    "value": 310,
    "taxonomy": "city_mulaware",
    "code1": null,
    "code2": "AR"
  },
  {
    "name": "Arauca",
    "value": 671,
    "taxonomy": "city_mulaware",
    "code1": null,
    "code2": "ARA"
  },
  {
    "name": "Arkhangelsk Oblast",
    "value": 102,
    "taxonomy": "city_mulaware",
    "code1": null,
    "code2": "ARK"
  },
  {
    "name": "American Samoa",
    "value": 60,
    "taxonomy": "city_mulaware",
    "code1": null,
    "code2": "AS"
  },
  {
    "name": "Assam",
    "value": 580,
    "taxonomy": "city_mulaware",
    "code1": null,
    "code2": "AS"
  },
  {
    "name": "Aswan",
    "value": 285,
    "taxonomy": "city_mulaware",
    "code1": null,
    "code2": "ASN"
  },
  {
    "name": "Astrakhan Oblast",
    "value": 103,
    "taxonomy": "city_mulaware",
    "code1": null,
    "code2": "AST"
  },
  {
    "name": "Asyut",
    "value": 286,
    "taxonomy": "city_mulaware",
    "code1": null,
    "code2": "AST"
  },
  {
    "name": "Asti",
    "value": 312,
    "taxonomy": "city_mulaware",
    "code1": null,
    "code2": "AT"
  },
  {
    "name": "Atlántico",
    "value": 648,
    "taxonomy": "city_mulaware",
    "code1": null,
    "code2": "ATL"
  },
  {
    "name": "Auckland",
    "value": 517,
    "taxonomy": "city_mulaware",
    "code1": null,
    "code2": "AUK"
  },
  {
    "name": "Ávila",
    "value": 423,
    "taxonomy": "city_mulaware",
    "code1": null,
    "code2": "AV"
  },
  {
    "name": "Avellino",
    "value": 313,
    "taxonomy": "city_mulaware",
    "code1": null,
    "code2": "AV"
  },
  {
    "name": "Alta Verapaz",
    "value": 179,
    "taxonomy": "city_mulaware",
    "code1": null,
    "code2": "AVE"
  },
  {
    "name": "Arizona",
    "value": 11,
    "taxonomy": "city_mulaware",
    "code1": null,
    "code2": "AZ"
  },
  {
    "name": "Abu Dhabi",
    "value": 546,
    "taxonomy": "city_mulaware",
    "code1": null,
    "code2": "AZ"
  },
  {
    "name": "Buenos Aires",
    "value": 554,
    "taxonomy": "city_mulaware",
    "code1": null,
    "code2": "B"
  },
  {
    "name": "Barcelona",
    "value": 426,
    "taxonomy": "city_mulaware",
    "code1": null,
    "code2": "B"
  },
  {
    "name": "Bari",
    "value": 314,
    "taxonomy": "city_mulaware",
    "code1": null,
    "code2": "BA"
  },
  {
    "name": "Bahia",
    "value": 75,
    "taxonomy": "city_mulaware",
    "code1": null,
    "code2": "BA"
  },
  {
    "name": "Republic of Bashkortostan",
    "value": 104,
    "taxonomy": "city_mulaware",
    "code1": null,
    "code2": "BA"
  },
  {
    "name": "Bali",
    "value": 614,
    "taxonomy": "city_mulaware",
    "code1": null,
    "code2": "BA"
  },
  {
    "name": "Red Sea",
    "value": 269,
    "taxonomy": "city_mulaware",
    "code1": null,
    "code2": "BA"
  },
  {
    "name": "Badajoz",
    "value": 424,
    "taxonomy": "city_mulaware",
    "code1": null,
    "code2": "BA"
  },
  {
    "name": "Bangka Belitung",
    "value": 615,
    "taxonomy": "city_mulaware",
    "code1": null,
    "code2": "BB"
  },
  {
    "name": "British Columbia",
    "value": 534,
    "taxonomy": "city_mulaware",
    "code1": null,
    "code2": "BC"
  },
  {
    "name": "Baja California",
    "value": 486,
    "taxonomy": "city_mulaware",
    "code1": null,
    "code2": "BCN"
  },
  {
    "name": "Baja California Sur",
    "value": 487,
    "taxonomy": "city_mulaware",
    "code1": null,
    "code2": "BCS"
  },
  {
    "name": "Bengkulu",
    "value": 617,
    "taxonomy": "city_mulaware",
    "code1": null,
    "code2": "BE"
  },
  {
    "name": "Belgorod Oblast",
    "value": 105,
    "taxonomy": "city_mulaware",
    "code1": null,
    "code2": "BEL"
  },
  {
    "name": "Bergamo",
    "value": 318,
    "taxonomy": "city_mulaware",
    "code1": null,
    "code2": "BG"
  },
  {
    "name": "Beheira",
    "value": 270,
    "taxonomy": "city_mulaware",
    "code1": null,
    "code2": "BH"
  },
  {
    "name": "Bizkaia (Vizcaya)",
    "value": 466,
    "taxonomy": "city_mulaware",
    "code1": null,
    "code2": "BI"
  },
  {
    "name": "Biella",
    "value": 319,
    "taxonomy": "city_mulaware",
    "code1": null,
    "code2": "BI"
  },
  {
    "name": "Belluno",
    "value": 316,
    "taxonomy": "city_mulaware",
    "code1": null,
    "code2": "BL"
  },
  {
    "name": "Benevento",
    "value": 317,
    "taxonomy": "city_mulaware",
    "code1": null,
    "code2": "BN"
  },
  {
    "name": "Beni Suef",
    "value": 287,
    "taxonomy": "city_mulaware",
    "code1": null,
    "code2": "BNS"
  },
  {
    "name": "Bologna",
    "value": 320,
    "taxonomy": "city_mulaware",
    "code1": null,
    "code2": "BO"
  },
  {
    "name": "Bolívar",
    "value": 650,
    "taxonomy": "city_mulaware",
    "code1": null,
    "code2": "BOL"
  },
  {
    "name": "Bay of Plenty",
    "value": 518,
    "taxonomy": "city_mulaware",
    "code1": null,
    "code2": "BOP"
  },
  {
    "name": "Boyacá",
    "value": 651,
    "taxonomy": "city_mulaware",
    "code1": null,
    "code2": "BOY"
  },
  {
    "name": "Bihar",
    "value": 581,
    "taxonomy": "city_mulaware",
    "code1": null,
    "code2": "BR"
  },
  {
    "name": "Brindisi",
    "value": 323,
    "taxonomy": "city_mulaware",
    "code1": null,
    "code2": "BR"
  },
  {
    "name": "Bryansk Oblast",
    "value": 106,
    "taxonomy": "city_mulaware",
    "code1": null,
    "code2": "BRY"
  },
  {
    "name": "Brescia",
    "value": 322,
    "taxonomy": "city_mulaware",
    "code1": null,
    "code2": "BS"
  },
  {
    "name": "Banten",
    "value": 616,
    "taxonomy": "city_mulaware",
    "code1": null,
    "code2": "BT"
  },
  {
    "name": "Barletta-Andria-Trani",
    "value": 315,
    "taxonomy": "city_mulaware",
    "code1": null,
    "code2": "BT"
  },
  {
    "name": "Burgos",
    "value": 427,
    "taxonomy": "city_mulaware",
    "code1": null,
    "code2": "BU"
  },
  {
    "name": "Republic of Buryatia",
    "value": 107,
    "taxonomy": "city_mulaware",
    "code1": null,
    "code2": "BU"
  },
  {
    "name": "Baja Verapaz",
    "value": 180,
    "taxonomy": "city_mulaware",
    "code1": null,
    "code2": "BVE"
  },
  {
    "name": "Bolzano",
    "value": 321,
    "taxonomy": "city_mulaware",
    "code1": null,
    "code2": "BZ"
  },
  {
    "name": "Cairo",
    "value": 278,
    "taxonomy": "city_mulaware",
    "code1": null,
    "code2": "C"
  },
  {
    "name": "A Coruña (La Coruña)",
    "value": 417,
    "taxonomy": "city_mulaware",
    "code1": null,
    "code2": "C"
  },
  {
    "name": "Ciudad Autónoma de Buenos Aires",
    "value": 553,
    "taxonomy": "city_mulaware",
    "code1": null,
    "code2": "C"
  },
  {
    "name": "Cádiz",
    "value": 429,
    "taxonomy": "city_mulaware",
    "code1": null,
    "code2": "CA"
  },
  {
    "name": "California",
    "value": 13,
    "taxonomy": "city_mulaware",
    "code1": null,
    "code2": "CA"
  },
  {
    "name": "Cagliari",
    "value": 324,
    "taxonomy": "city_mulaware",
    "code1": null,
    "code2": "CA"
  },
  {
    "name": "Caldas",
    "value": 652,
    "taxonomy": "city_mulaware",
    "code1": null,
    "code2": "CAL"
  },
  {
    "name": "Campeche",
    "value": 490,
    "taxonomy": "city_mulaware",
    "code1": null,
    "code2": "CAM"
  },
  {
    "name": "Canterbury",
    "value": 519,
    "taxonomy": "city_mulaware",
    "code1": null,
    "code2": "CAN"
  },
  {
    "name": "Caquetá",
    "value": 653,
    "taxonomy": "city_mulaware",
    "code1": null,
    "code2": "CAQ"
  },
  {
    "name": "Casanare",
    "value": 672,
    "taxonomy": "city_mulaware",
    "code1": null,
    "code2": "CAS"
  },
  {
    "name": "Cauca",
    "value": 654,
    "taxonomy": "city_mulaware",
    "code1": null,
    "code2": "CAU"
  },
  {
    "name": "Campobasso",
    "value": 326,
    "taxonomy": "city_mulaware",
    "code1": null,
    "code2": "CB"
  },
  {
    "name": "Cáceres",
    "value": 428,
    "taxonomy": "city_mulaware",
    "code1": null,
    "code2": "CC"
  },
  {
    "name": "Chechen Republic",
    "value": 108,
    "taxonomy": "city_mulaware",
    "code1": null,
    "code2": "CE"
  },
  {
    "name": "Ceará",
    "value": 76,
    "taxonomy": "city_mulaware",
    "code1": null,
    "code2": "CE"
  },
  {
    "name": "Caserta",
    "value": 328,
    "taxonomy": "city_mulaware",
    "code1": null,
    "code2": "CE"
  },
  {
    "name": "Ceuta",
    "value": 432,
    "taxonomy": "city_mulaware",
    "code1": null,
    "code2": "CE"
  },
  {
    "name": "Cesar",
    "value": 655,
    "taxonomy": "city_mulaware",
    "code1": null,
    "code2": "CES"
  },
  {
    "name": "Chattisgarh",
    "value": 583,
    "taxonomy": "city_mulaware",
    "code1": null,
    "code2": "CG"
  },
  {
    "name": "Chieti",
    "value": 331,
    "taxonomy": "city_mulaware",
    "code1": null,
    "code2": "CH"
  },
  {
    "name": "Chandigarh",
    "value": 582,
    "taxonomy": "city_mulaware",
    "code1": null,
    "code2": "CH"
  },
  {
    "name": "Chelyabinsk Oblast",
    "value": 109,
    "taxonomy": "city_mulaware",
    "code1": null,
    "code2": "CHE"
  },
  {
    "name": "Chihuahua",
    "value": 488,
    "taxonomy": "city_mulaware",
    "code1": null,
    "code2": "CHH"
  },
  {
    "name": "Chocó",
    "value": 658,
    "taxonomy": "city_mulaware",
    "code1": null,
    "code2": "CHO"
  },
  {
    "name": "Chiapas",
    "value": 492,
    "taxonomy": "city_mulaware",
    "code1": null,
    "code2": "CHP"
  },
  {
    "name": "Chukotka Autonomous Okrug",
    "value": 110,
    "taxonomy": "city_mulaware",
    "code1": null,
    "code2": "CHU"
  },
  {
    "name": "Carbonia-Iglesias",
    "value": 327,
    "taxonomy": "city_mulaware",
    "code1": null,
    "code2": "CI"
  },
  {
    "name": "Caltanissetta",
    "value": 325,
    "taxonomy": "city_mulaware",
    "code1": null,
    "code2": "CL"
  },
  {
    "name": "Chimaltenango",
    "value": 181,
    "taxonomy": "city_mulaware",
    "code1": null,
    "code2": "CMT"
  },
  {
    "name": "Cuneo",
    "value": 336,
    "taxonomy": "city_mulaware",
    "code1": null,
    "code2": "CN"
  },
  {
    "name": "Córdoba",
    "value": 434,
    "taxonomy": "city_mulaware",
    "code1": null,
    "code2": "CO"
  },
  {
    "name": "Como",
    "value": 332,
    "taxonomy": "city_mulaware",
    "code1": null,
    "code2": "CO"
  },
  {
    "name": "Colorado",
    "value": 14,
    "taxonomy": "city_mulaware",
    "code1": null,
    "code2": "CO"
  },
  {
    "name": "Coahuila",
    "value": 491,
    "taxonomy": "city_mulaware",
    "code1": null,
    "code2": "COA"
  },
  {
    "name": "Colima",
    "value": 489,
    "taxonomy": "city_mulaware",
    "code1": null,
    "code2": "COL"
  },
  {
    "name": "Córdoba",
    "value": 656,
    "taxonomy": "city_mulaware",
    "code1": null,
    "code2": "COR"
  },
  {
    "name": "Chiquimula",
    "value": 182,
    "taxonomy": "city_mulaware",
    "code1": null,
    "code2": "CQM"
  },
  {
    "name": "Cremona",
    "value": 334,
    "taxonomy": "city_mulaware",
    "code1": null,
    "code2": "CR"
  },
  {
    "name": "Ciudad Real",
    "value": 433,
    "taxonomy": "city_mulaware",
    "code1": null,
    "code2": "CR"
  },
  {
    "name": "Cosenza",
    "value": 333,
    "taxonomy": "city_mulaware",
    "code1": null,
    "code2": "CS"
  },
  {
    "name": "Castelló (Castellón)",
    "value": 431,
    "taxonomy": "city_mulaware",
    "code1": null,
    "code2": "CS"
  },
  {
    "name": "Connecticut",
    "value": 15,
    "taxonomy": "city_mulaware",
    "code1": null,
    "code2": "CT"
  },
  {
    "name": "Catania",
    "value": 329,
    "taxonomy": "city_mulaware",
    "code1": null,
    "code2": "CT"
  },
  {
    "name": "Cuenca",
    "value": 435,
    "taxonomy": "city_mulaware",
    "code1": null,
    "code2": "CU"
  },
  {
    "name": "Chuvash Republic",
    "value": 111,
    "taxonomy": "city_mulaware",
    "code1": null,
    "code2": "CU"
  },
  {
    "name": "Cundinamarca",
    "value": 657,
    "taxonomy": "city_mulaware",
    "code1": null,
    "code2": "CUN"
  },
  {
    "name": "Catanzaro",
    "value": 330,
    "taxonomy": "city_mulaware",
    "code1": null,
    "code2": "CZ"
  },
  {
    "name": "San Luis",
    "value": 571,
    "taxonomy": "city_mulaware",
    "code1": null,
    "code2": "D"
  },
  {
    "name": "Republic of Dagestan",
    "value": 112,
    "taxonomy": "city_mulaware",
    "code1": null,
    "code2": "DA"
  },
  {
    "name": "District of Columbia",
    "value": 17,
    "taxonomy": "city_mulaware",
    "code1": null,
    "code2": "DC"
  },
  {
    "name": "D.C.",
    "value": 649,
    "taxonomy": "city_mulaware",
    "code1": null,
    "code2": "DC"
  },
  {
    "name": "Daman and Diu",
    "value": 585,
    "taxonomy": "city_mulaware",
    "code1": null,
    "code2": "DD"
  },
  {
    "name": "Delaware",
    "value": 16,
    "taxonomy": "city_mulaware",
    "code1": null,
    "code2": "DE"
  },
  {
    "name": "Distrito Federal",
    "value": 77,
    "taxonomy": "city_mulaware",
    "code1": null,
    "code2": "DF"
  },
  {
    "name": "Ciudad de México",
    "value": 493,
    "taxonomy": "city_mulaware",
    "code1": null,
    "code2": "DIF"
  },
  {
    "name": "Dakahlia",
    "value": 268,
    "taxonomy": "city_mulaware",
    "code1": null,
    "code2": "DK"
  },
  {
    "name": "Delhi",
    "value": 586,
    "taxonomy": "city_mulaware",
    "code1": null,
    "code2": "DL"
  },
  {
    "name": "Dadra and Nagar Haveli",
    "value": 584,
    "taxonomy": "city_mulaware",
    "code1": null,
    "code2": "DN"
  },
  {
    "name": "Damietta",
    "value": 289,
    "taxonomy": "city_mulaware",
    "code1": null,
    "code2": "DT"
  },
  {
    "name": "Dubai",
    "value": 548,
    "taxonomy": "city_mulaware",
    "code1": null,
    "code2": "DU"
  },
  {
    "name": "Durango",
    "value": 494,
    "taxonomy": "city_mulaware",
    "code1": null,
    "code2": "DUR"
  },
  {
    "name": "Entre Ríos",
    "value": 560,
    "taxonomy": "city_mulaware",
    "code1": null,
    "code2": "E"
  },
  {
    "name": "Eastern Cape",
    "value": 297,
    "taxonomy": "city_mulaware",
    "code1": null,
    "code2": "EC"
  },
  {
    "name": "Enna",
    "value": 337,
    "taxonomy": "city_mulaware",
    "code1": null,
    "code2": "EN"
  },
  {
    "name": "El Progreso",
    "value": 183,
    "taxonomy": "city_mulaware",
    "code1": null,
    "code2": "EPR"
  },
  {
    "name": "Espírito Santo",
    "value": 78,
    "taxonomy": "city_mulaware",
    "code1": null,
    "code2": "ES"
  },
  {
    "name": "Escuintla",
    "value": 184,
    "taxonomy": "city_mulaware",
    "code1": null,
    "code2": "ESC"
  },
  {
    "name": "La Rioja",
    "value": 564,
    "taxonomy": "city_mulaware",
    "code1": null,
    "code2": "F"
  },
  {
    "name": "Forlì-Cesena",
    "value": 342,
    "taxonomy": "city_mulaware",
    "code1": null,
    "code2": "FC"
  },
  {
    "name": "Ferrara",
    "value": 339,
    "taxonomy": "city_mulaware",
    "code1": null,
    "code2": "FE"
  },
  {
    "name": "Foggia",
    "value": 341,
    "taxonomy": "city_mulaware",
    "code1": null,
    "code2": "FG"
  },
  {
    "name": "Firenze",
    "value": 340,
    "taxonomy": "city_mulaware",
    "code1": null,
    "code2": "FI"
  },
  {
    "name": "Florida",
    "value": 18,
    "taxonomy": "city_mulaware",
    "code1": null,
    "code2": "FL"
  },
  {
    "name": "Fermo",
    "value": 338,
    "taxonomy": "city_mulaware",
    "code1": null,
    "code2": "FM"
  },
  {
    "name": "Federated States of Micronesia",
    "value": 61,
    "taxonomy": "city_mulaware",
    "code1": null,
    "code2": "FM"
  },
  {
    "name": "Frosinone",
    "value": 343,
    "taxonomy": "city_mulaware",
    "code1": null,
    "code2": "FR"
  },
  {
    "name": "Free State",
    "value": 298,
    "taxonomy": "city_mulaware",
    "code1": null,
    "code2": "FS"
  },
  {
    "name": "Fujairah",
    "value": 549,
    "taxonomy": "city_mulaware",
    "code1": null,
    "code2": "FU"
  },
  {
    "name": "Faiyum",
    "value": 271,
    "taxonomy": "city_mulaware",
    "code1": null,
    "code2": "FYM"
  },
  {
    "name": "Santiago Del Estero",
    "value": 574,
    "taxonomy": "city_mulaware",
    "code1": null,
    "code2": "G"
  },
  {
    "name": "Goa",
    "value": 587,
    "taxonomy": "city_mulaware",
    "code1": null,
    "code2": "GA"
  },
  {
    "name": "Georgia",
    "value": 19,
    "taxonomy": "city_mulaware",
    "code1": null,
    "code2": "GA"
  },
  {
    "name": "Las Palmas",
    "value": 444,
    "taxonomy": "city_mulaware",
    "code1": null,
    "code2": "GC"
  },
  {
    "name": "Genova",
    "value": 344,
    "taxonomy": "city_mulaware",
    "code1": null,
    "code2": "GE"
  },
  {
    "name": "Gharbia",
    "value": 272,
    "taxonomy": "city_mulaware",
    "code1": null,
    "code2": "GH"
  },
  {
    "name": "Girona (Gerona)",
    "value": 436,
    "taxonomy": "city_mulaware",
    "code1": null,
    "code2": "GI"
  },
  {
    "name": "Gisborne",
    "value": 520,
    "taxonomy": "city_mulaware",
    "code1": null,
    "code2": "GIS"
  },
  {
    "name": "Gujarat",
    "value": 588,
    "taxonomy": "city_mulaware",
    "code1": null,
    "code2": "GJ"
  },
  {
    "name": "Gorizia",
    "value": 345,
    "taxonomy": "city_mulaware",
    "code1": null,
    "code2": "GO"
  },
  {
    "name": "Gorontalo",
    "value": 618,
    "taxonomy": "city_mulaware",
    "code1": null,
    "code2": "GO"
  },
  {
    "name": "Goiás",
    "value": 79,
    "taxonomy": "city_mulaware",
    "code1": null,
    "code2": "GO"
  },
  {
    "name": "Grosseto",
    "value": 346,
    "taxonomy": "city_mulaware",
    "code1": null,
    "code2": "GR"
  },
  {
    "name": "Granada",
    "value": 437,
    "taxonomy": "city_mulaware",
    "code1": null,
    "code2": "GR"
  },
  {
    "name": "Guerrero",
    "value": 495,
    "taxonomy": "city_mulaware",
    "code1": null,
    "code2": "GRO"
  },
  {
    "name": "Gauteng",
    "value": 299,
    "taxonomy": "city_mulaware",
    "code1": null,
    "code2": "GT"
  },
  {
    "name": "Guam",
    "value": 62,
    "taxonomy": "city_mulaware",
    "code1": null,
    "code2": "GU"
  },
  {
    "name": "Guadalajara",
    "value": 438,
    "taxonomy": "city_mulaware",
    "code1": null,
    "code2": "GU"
  },
  {
    "name": "Guainía",
    "value": 676,
    "taxonomy": "city_mulaware",
    "code1": null,
    "code2": "GUA"
  },
  {
    "name": "Guatemala",
    "value": 185,
    "taxonomy": "city_mulaware",
    "code1": null,
    "code2": "GUA"
  },
  {
    "name": "Guanajuato",
    "value": 496,
    "taxonomy": "city_mulaware",
    "code1": null,
    "code2": "GUA"
  },
  {
    "name": "Guaviare",
    "value": 677,
    "taxonomy": "city_mulaware",
    "code1": null,
    "code2": "GUV"
  },
  {
    "name": "Giza",
    "value": 275,
    "taxonomy": "city_mulaware",
    "code1": null,
    "code2": "GZ"
  },
  {
    "name": "Huelva",
    "value": 440,
    "taxonomy": "city_mulaware",
    "code1": null,
    "code2": "H"
  },
  {
    "name": "Chaco",
    "value": 556,
    "taxonomy": "city_mulaware",
    "code1": null,
    "code2": "H"
  },
  {
    "name": "Hawaii",
    "value": 20,
    "taxonomy": "city_mulaware",
    "code1": null,
    "code2": "HI"
  },
  {
    "name": "Hidalgo",
    "value": 497,
    "taxonomy": "city_mulaware",
    "code1": null,
    "code2": "HID"
  },
  {
    "name": "Hawke's Bay",
    "value": 521,
    "taxonomy": "city_mulaware",
    "code1": null,
    "code2": "HKB"
  },
  {
    "name": "Himachal Pradesh",
    "value": 590,
    "taxonomy": "city_mulaware",
    "code1": null,
    "code2": "HP"
  },
  {
    "name": "Haryana",
    "value": 589,
    "taxonomy": "city_mulaware",
    "code1": null,
    "code2": "HR"
  },
  {
    "name": "Huesca",
    "value": 441,
    "taxonomy": "city_mulaware",
    "code1": null,
    "code2": "HU"
  },
  {
    "name": "Helwan",
    "value": 290,
    "taxonomy": "city_mulaware",
    "code1": null,
    "code2": "HU"
  },
  {
    "name": "Huehuetenango",
    "value": 186,
    "taxonomy": "city_mulaware",
    "code1": null,
    "code2": "HUE"
  },
  {
    "name": "Huila",
    "value": 659,
    "taxonomy": "city_mulaware",
    "code1": null,
    "code2": "HUI"
  },
  {
    "name": "Iowa",
    "value": 24,
    "taxonomy": "city_mulaware",
    "code1": null,
    "code2": "IA"
  },
  {
    "name": "Idaho",
    "value": 21,
    "taxonomy": "city_mulaware",
    "code1": null,
    "code2": "ID"
  },
  {
    "name": "Illinois",
    "value": 22,
    "taxonomy": "city_mulaware",
    "code1": null,
    "code2": "IL"
  },
  {
    "name": "Imperia",
    "value": 347,
    "taxonomy": "city_mulaware",
    "code1": null,
    "code2": "IM"
  },
  {
    "name": "Indiana",
    "value": 23,
    "taxonomy": "city_mulaware",
    "code1": null,
    "code2": "IN"
  },
  {
    "name": "Republic of Ingushetia",
    "value": 113,
    "taxonomy": "city_mulaware",
    "code1": null,
    "code2": "IN"
  },
  {
    "name": "Irkutsk Oblast",
    "value": 114,
    "taxonomy": "city_mulaware",
    "code1": null,
    "code2": "IRK"
  },
  {
    "name": "Ismailia",
    "value": 274,
    "taxonomy": "city_mulaware",
    "code1": null,
    "code2": "IS"
  },
  {
    "name": "Isernia",
    "value": 348,
    "taxonomy": "city_mulaware",
    "code1": null,
    "code2": "IS"
  },
  {
    "name": "Ivanovo Oblast",
    "value": 115,
    "taxonomy": "city_mulaware",
    "code1": null,
    "code2": "IVA"
  },
  {
    "name": "Izabal",
    "value": 187,
    "taxonomy": "city_mulaware",
    "code1": null,
    "code2": "IZA"
  },
  {
    "name": "Jaén",
    "value": 442,
    "taxonomy": "city_mulaware",
    "code1": null,
    "code2": "J"
  },
  {
    "name": "San Juan",
    "value": 570,
    "taxonomy": "city_mulaware",
    "code1": null,
    "code2": "J"
  },
  {
    "name": "Jambi",
    "value": 620,
    "taxonomy": "city_mulaware",
    "code1": null,
    "code2": "JA"
  },
  {
    "name": "Jalapa",
    "value": 188,
    "taxonomy": "city_mulaware",
    "code1": null,
    "code2": "JAL"
  },
  {
    "name": "Jalisco",
    "value": 498,
    "taxonomy": "city_mulaware",
    "code1": null,
    "code2": "JAL"
  },
  {
    "name": "Jawa Barat",
    "value": 621,
    "taxonomy": "city_mulaware",
    "code1": null,
    "code2": "JB"
  },
  {
    "name": "Jharkhand",
    "value": 592,
    "taxonomy": "city_mulaware",
    "code1": null,
    "code2": "JH"
  },
  {
    "name": "Johor",
    "value": 469,
    "taxonomy": "city_mulaware",
    "code1": null,
    "code2": "JHR"
  },
  {
    "name": "Jawa Timur",
    "value": 623,
    "taxonomy": "city_mulaware",
    "code1": null,
    "code2": "JI"
  },
  {
    "name": "Jakarta",
    "value": 619,
    "taxonomy": "city_mulaware",
    "code1": null,
    "code2": "JK"
  },
  {
    "name": "Jammu and Kashmir",
    "value": 591,
    "taxonomy": "city_mulaware",
    "code1": null,
    "code2": "JK"
  },
  {
    "name": "South Sinai",
    "value": 291,
    "taxonomy": "city_mulaware",
    "code1": null,
    "code2": "JS"
  },
  {
    "name": "Jawa Tengah",
    "value": 622,
    "taxonomy": "city_mulaware",
    "code1": null,
    "code2": "JT"
  },
  {
    "name": "Jutiapa",
    "value": 189,
    "taxonomy": "city_mulaware",
    "code1": null,
    "code2": "JUT"
  },
  {
    "name": "Catamarca",
    "value": 555,
    "taxonomy": "city_mulaware",
    "code1": null,
    "code2": "K"
  },
  {
    "name": "Karnataka",
    "value": 593,
    "taxonomy": "city_mulaware",
    "code1": null,
    "code2": "KA"
  },
  {
    "name": "Kamchatka Krai",
    "value": 116,
    "taxonomy": "city_mulaware",
    "code1": null,
    "code2": "KAM"
  },
  {
    "name": "Qalyubia",
    "value": 279,
    "taxonomy": "city_mulaware",
    "code1": null,
    "code2": "KB"
  },
  {
    "name": "Kabardino-Balkarian Republic",
    "value": 117,
    "taxonomy": "city_mulaware",
    "code1": null,
    "code2": "KB"
  },
  {
    "name": "Kalimantan Barat",
    "value": 624,
    "taxonomy": "city_mulaware",
    "code1": null,
    "code2": "KB"
  },
  {
    "name": "Karachay–Cherkess Republic",
    "value": 121,
    "taxonomy": "city_mulaware",
    "code1": null,
    "code2": "KC"
  },
  {
    "name": "Krasnodar Krai",
    "value": 130,
    "taxonomy": "city_mulaware",
    "code1": null,
    "code2": "KDA"
  },
  {
    "name": "Kedah",
    "value": 470,
    "taxonomy": "city_mulaware",
    "code1": null,
    "code2": "KDH"
  },
  {
    "name": "Kemerovo Oblast",
    "value": 123,
    "taxonomy": "city_mulaware",
    "code1": null,
    "code2": "KEM"
  },
  {
    "name": "Kafr el-Sheikh",
    "value": 292,
    "taxonomy": "city_mulaware",
    "code1": null,
    "code2": "KFS"
  },
  {
    "name": "Kaliningrad Oblast",
    "value": 118,
    "taxonomy": "city_mulaware",
    "code1": null,
    "code2": "KGD"
  },
  {
    "name": "Kurgan Oblast",
    "value": 132,
    "taxonomy": "city_mulaware",
    "code1": null,
    "code2": "KGN"
  },
  {
    "name": "Khabarovsk Krai",
    "value": 124,
    "taxonomy": "city_mulaware",
    "code1": null,
    "code2": "KHA"
  },
  {
    "name": "Khanty-Mansi Autonomous Okrug",
    "value": 126,
    "taxonomy": "city_mulaware",
    "code1": null,
    "code2": "KHM"
  },
  {
    "name": "Kalimantan Timur",
    "value": 627,
    "taxonomy": "city_mulaware",
    "code1": null,
    "code2": "KI"
  },
  {
    "name": "Kirov Oblast",
    "value": 127,
    "taxonomy": "city_mulaware",
    "code1": null,
    "code2": "KIR"
  },
  {
    "name": "Republic of Khakassia",
    "value": 125,
    "taxonomy": "city_mulaware",
    "code1": null,
    "code2": "KK"
  },
  {
    "name": "Republic of Kalmykia",
    "value": 119,
    "taxonomy": "city_mulaware",
    "code1": null,
    "code2": "KL"
  },
  {
    "name": "Kerala",
    "value": 594,
    "taxonomy": "city_mulaware",
    "code1": null,
    "code2": "KL"
  },
  {
    "name": "Kaluga Oblast",
    "value": 120,
    "taxonomy": "city_mulaware",
    "code1": null,
    "code2": "KLU"
  },
  {
    "name": "Qena",
    "value": 294,
    "taxonomy": "city_mulaware",
    "code1": null,
    "code2": "KN"
  },
  {
    "name": "Komi Republic",
    "value": 128,
    "taxonomy": "city_mulaware",
    "code1": null,
    "code2": "KO"
  },
  {
    "name": "Kostroma Oblast",
    "value": 129,
    "taxonomy": "city_mulaware",
    "code1": null,
    "code2": "KOS"
  },
  {
    "name": "Crotone",
    "value": 335,
    "taxonomy": "city_mulaware",
    "code1": null,
    "code2": "KR"
  },
  {
    "name": "Kepulauan Riau",
    "value": 629,
    "taxonomy": "city_mulaware",
    "code1": null,
    "code2": "KR"
  },
  {
    "name": "Republic of Karelia",
    "value": 122,
    "taxonomy": "city_mulaware",
    "code1": null,
    "code2": "KR"
  },
  {
    "name": "Kursk Oblast",
    "value": 133,
    "taxonomy": "city_mulaware",
    "code1": null,
    "code2": "KRS"
  },
  {
    "name": "Kalimantan Selatan",
    "value": 625,
    "taxonomy": "city_mulaware",
    "code1": null,
    "code2": "KS"
  },
  {
    "name": "Kansas",
    "value": 25,
    "taxonomy": "city_mulaware",
    "code1": null,
    "code2": "KS"
  },
  {
    "name": "Kalimantan Tengah",
    "value": 626,
    "taxonomy": "city_mulaware",
    "code1": null,
    "code2": "KT"
  },
  {
    "name": "Kelantan",
    "value": 471,
    "taxonomy": "city_mulaware",
    "code1": null,
    "code2": "KTN"
  },
  {
    "name": "Kalimantan Utara",
    "value": 628,
    "taxonomy": "city_mulaware",
    "code1": null,
    "code2": "KU"
  },
  {
    "name": "Kuala Lumpur",
    "value": 472,
    "taxonomy": "city_mulaware",
    "code1": null,
    "code2": "KUL"
  },
  {
    "name": "Kentucky",
    "value": 26,
    "taxonomy": "city_mulaware",
    "code1": null,
    "code2": "KY"
  },
  {
    "name": "Krasnoyarsk Krai",
    "value": 131,
    "taxonomy": "city_mulaware",
    "code1": null,
    "code2": "KYA"
  },
  {
    "name": "Lleida (Lérida)",
    "value": 446,
    "taxonomy": "city_mulaware",
    "code1": null,
    "code2": "L"
  },
  {
    "name": "La Pampa",
    "value": 563,
    "taxonomy": "city_mulaware",
    "code1": null,
    "code2": "L"
  },
  {
    "name": "Louisiana",
    "value": 27,
    "taxonomy": "city_mulaware",
    "code1": null,
    "code2": "LA"
  },
  {
    "name": "Lampung",
    "value": 630,
    "taxonomy": "city_mulaware",
    "code1": null,
    "code2": "LA"
  },
  {
    "name": "La Guajira",
    "value": 660,
    "taxonomy": "city_mulaware",
    "code1": null,
    "code2": "LAG"
  },
  {
    "name": "Labuan",
    "value": 473,
    "taxonomy": "city_mulaware",
    "code1": null,
    "code2": "LBN"
  },
  {
    "name": "Lecco",
    "value": 353,
    "taxonomy": "city_mulaware",
    "code1": null,
    "code2": "LC"
  },
  {
    "name": "Lakshadweep",
    "value": 595,
    "taxonomy": "city_mulaware",
    "code1": null,
    "code2": "LD"
  },
  {
    "name": "León",
    "value": 445,
    "taxonomy": "city_mulaware",
    "code1": null,
    "code2": "LE"
  },
  {
    "name": "Lecce",
    "value": 352,
    "taxonomy": "city_mulaware",
    "code1": null,
    "code2": "LE"
  },
  {
    "name": "Leningrad Oblast",
    "value": 134,
    "taxonomy": "city_mulaware",
    "code1": null,
    "code2": "LEN"
  },
  {
    "name": "Livorno",
    "value": 354,
    "taxonomy": "city_mulaware",
    "code1": null,
    "code2": "LI"
  },
  {
    "name": "Lipetsk Oblast",
    "value": 135,
    "taxonomy": "city_mulaware",
    "code1": null,
    "code2": "LIP"
  },
  {
    "name": "La Rioja",
    "value": 443,
    "taxonomy": "city_mulaware",
    "code1": null,
    "code2": "LO"
  },
  {
    "name": "Lodi",
    "value": 355,
    "taxonomy": "city_mulaware",
    "code1": null,
    "code2": "LO"
  },
  {
    "name": "Limpopo",
    "value": 301,
    "taxonomy": "city_mulaware",
    "code1": null,
    "code2": "LP"
  },
  {
    "name": "Latina",
    "value": 351,
    "taxonomy": "city_mulaware",
    "code1": null,
    "code2": "LT"
  },
  {
    "name": "Lugo",
    "value": 447,
    "taxonomy": "city_mulaware",
    "code1": null,
    "code2": "LU"
  },
  {
    "name": "Lucca",
    "value": 356,
    "taxonomy": "city_mulaware",
    "code1": null,
    "code2": "LU"
  },
  {
    "name": "Luxor",
    "value": 280,
    "taxonomy": "city_mulaware",
    "code1": null,
    "code2": "LX"
  },
  {
    "name": "Mendoza",
    "value": 565,
    "taxonomy": "city_mulaware",
    "code1": null,
    "code2": "M"
  },
  {
    "name": "Madrid",
    "value": 448,
    "taxonomy": "city_mulaware",
    "code1": null,
    "code2": "M"
  },
  {
    "name": "Maluku",
    "value": 631,
    "taxonomy": "city_mulaware",
    "code1": null,
    "code2": "MA"
  },
  {
    "name": "Massachusetts",
    "value": 42,
    "taxonomy": "city_mulaware",
    "code1": null,
    "code2": "MA"
  },
  {
    "name": "Maranhão",
    "value": 80,
    "taxonomy": "city_mulaware",
    "code1": null,
    "code2": "MA"
  },
  {
    "name": "Málaga",
    "value": 449,
    "taxonomy": "city_mulaware",
    "code1": null,
    "code2": "MA"
  },
  {
    "name": "Magadan Oblast",
    "value": 136,
    "taxonomy": "city_mulaware",
    "code1": null,
    "code2": "MAG"
  },
  {
    "name": "Magdalena",
    "value": 661,
    "taxonomy": "city_mulaware",
    "code1": null,
    "code2": "MAG"
  },
  {
    "name": "Monza e Brianza",
    "value": 365,
    "taxonomy": "city_mulaware",
    "code1": null,
    "code2": "MB"
  },
  {
    "name": "Manitoba",
    "value": 535,
    "taxonomy": "city_mulaware",
    "code1": null,
    "code2": "MB"
  },
  {
    "name": "Marlborough",
    "value": 523,
    "taxonomy": "city_mulaware",
    "code1": null,
    "code2": "MBH"
  },
  {
    "name": "Macerata",
    "value": 357,
    "taxonomy": "city_mulaware",
    "code1": null,
    "code2": "MC"
  },
  {
    "name": "Maryland",
    "value": 41,
    "taxonomy": "city_mulaware",
    "code1": null,
    "code2": "MD"
  },
  {
    "name": "Maine",
    "value": 28,
    "taxonomy": "city_mulaware",
    "code1": null,
    "code2": "ME"
  },
  {
    "name": "Mari El Republic",
    "value": 137,
    "taxonomy": "city_mulaware",
    "code1": null,
    "code2": "ME"
  },
  {
    "name": "Melilla",
    "value": 450,
    "taxonomy": "city_mulaware",
    "code1": null,
    "code2": "ME"
  },
  {
    "name": "Messina",
    "value": 362,
    "taxonomy": "city_mulaware",
    "code1": null,
    "code2": "ME"
  },
  {
    "name": "Meta",
    "value": 662,
    "taxonomy": "city_mulaware",
    "code1": null,
    "code2": "MET"
  },
  {
    "name": "México",
    "value": 501,
    "taxonomy": "city_mulaware",
    "code1": null,
    "code2": "MEX"
  },
  {
    "name": "Minas Gerais",
    "value": 83,
    "taxonomy": "city_mulaware",
    "code1": null,
    "code2": "MG"
  },
  {
    "name": "Marshall Islands",
    "value": 63,
    "taxonomy": "city_mulaware",
    "code1": null,
    "code2": "MH"
  },
  {
    "name": "Maharashtra",
    "value": 597,
    "taxonomy": "city_mulaware",
    "code1": null,
    "code2": "MH"
  },
  {
    "name": "Milano",
    "value": 363,
    "taxonomy": "city_mulaware",
    "code1": null,
    "code2": "MI"
  },
  {
    "name": "Michigan",
    "value": 43,
    "taxonomy": "city_mulaware",
    "code1": null,
    "code2": "MI"
  },
  {
    "name": "Michoacán",
    "value": 499,
    "taxonomy": "city_mulaware",
    "code1": null,
    "code2": "MIC"
  },
  {
    "name": "Meghalaya",
    "value": 599,
    "taxonomy": "city_mulaware",
    "code1": null,
    "code2": "ML"
  },
  {
    "name": "Melaka",
    "value": 474,
    "taxonomy": "city_mulaware",
    "code1": null,
    "code2": "MLK"
  },
  {
    "name": "Mantova",
    "value": 358,
    "taxonomy": "city_mulaware",
    "code1": null,
    "code2": "MN"
  },
  {
    "name": "Manipur",
    "value": 598,
    "taxonomy": "city_mulaware",
    "code1": null,
    "code2": "MN"
  },
  {
    "name": "Minya",
    "value": 277,
    "taxonomy": "city_mulaware",
    "code1": null,
    "code2": "MN"
  },
  {
    "name": "Minnesota",
    "value": 44,
    "taxonomy": "city_mulaware",
    "code1": null,
    "code2": "MN"
  },
  {
    "name": "Monufia",
    "value": 276,
    "taxonomy": "city_mulaware",
    "code1": null,
    "code2": "MNF"
  },
  {
    "name": "Modena",
    "value": 364,
    "taxonomy": "city_mulaware",
    "code1": null,
    "code2": "MO"
  },
  {
    "name": "Missouri",
    "value": 46,
    "taxonomy": "city_mulaware",
    "code1": null,
    "code2": "MO"
  },
  {
    "name": "Republic of Mordovia",
    "value": 138,
    "taxonomy": "city_mulaware",
    "code1": null,
    "code2": "MO"
  },
  {
    "name": "Morelos",
    "value": 500,
    "taxonomy": "city_mulaware",
    "code1": null,
    "code2": "MOR"
  },
  {
    "name": "Moscow Oblast",
    "value": 139,
    "taxonomy": "city_mulaware",
    "code1": null,
    "code2": "MOS"
  },
  {
    "name": "Moscow",
    "value": 140,
    "taxonomy": "city_mulaware",
    "code1": null,
    "code2": "MOW"
  },
  {
    "name": "Mpumalanga",
    "value": 302,
    "taxonomy": "city_mulaware",
    "code1": null,
    "code2": "MP"
  },
  {
    "name": "Madhya Pradesh",
    "value": 596,
    "taxonomy": "city_mulaware",
    "code1": null,
    "code2": "MP"
  },
  {
    "name": "Northern Mariana Islands",
    "value": 64,
    "taxonomy": "city_mulaware",
    "code1": null,
    "code2": "MP"
  },
  {
    "name": "Mato Grosso do Sul",
    "value": 82,
    "taxonomy": "city_mulaware",
    "code1": null,
    "code2": "MS"
  },
  {
    "name": "Massa-Carrara",
    "value": 359,
    "taxonomy": "city_mulaware",
    "code1": null,
    "code2": "MS"
  },
  {
    "name": "Mississippi",
    "value": 45,
    "taxonomy": "city_mulaware",
    "code1": null,
    "code2": "MS"
  },
  {
    "name": "Matera",
    "value": 360,
    "taxonomy": "city_mulaware",
    "code1": null,
    "code2": "MT"
  },
  {
    "name": "Matrouh",
    "value": 293,
    "taxonomy": "city_mulaware",
    "code1": null,
    "code2": "MT"
  },
  {
    "name": "Mato Grosso",
    "value": 81,
    "taxonomy": "city_mulaware",
    "code1": null,
    "code2": "MT"
  },
  {
    "name": "Montana",
    "value": 29,
    "taxonomy": "city_mulaware",
    "code1": null,
    "code2": "MT"
  },
  {
    "name": "Maluku Utara",
    "value": 632,
    "taxonomy": "city_mulaware",
    "code1": null,
    "code2": "MU"
  },
  {
    "name": "Murcia",
    "value": 451,
    "taxonomy": "city_mulaware",
    "code1": null,
    "code2": "MU"
  },
  {
    "name": "Murmansk Oblast",
    "value": 141,
    "taxonomy": "city_mulaware",
    "code1": null,
    "code2": "MUR"
  },
  {
    "name": "Manawatu-Wanganui",
    "value": 522,
    "taxonomy": "city_mulaware",
    "code1": null,
    "code2": "MWT"
  },
  {
    "name": "Mizoram",
    "value": 600,
    "taxonomy": "city_mulaware",
    "code1": null,
    "code2": "MZ"
  },
  {
    "name": "Misiones",
    "value": 566,
    "taxonomy": "city_mulaware",
    "code1": null,
    "code2": "N"
  },
  {
    "name": "Napoli",
    "value": 366,
    "taxonomy": "city_mulaware",
    "code1": null,
    "code2": "NA"
  },
  {
    "name": "Navarra (Nafarroa)",
    "value": 452,
    "taxonomy": "city_mulaware",
    "code1": null,
    "code2": "NA"
  },
  {
    "name": "Nariño",
    "value": 663,
    "taxonomy": "city_mulaware",
    "code1": null,
    "code2": "NAR"
  },
  {
    "name": "Nayarit",
    "value": 502,
    "taxonomy": "city_mulaware",
    "code1": null,
    "code2": "NAY"
  },
  {
    "name": "New Brunswick",
    "value": 536,
    "taxonomy": "city_mulaware",
    "code1": null,
    "code2": "NB"
  },
  {
    "name": "Nusa Tenggara Barat",
    "value": 633,
    "taxonomy": "city_mulaware",
    "code1": null,
    "code2": "NB"
  },
  {
    "name": "North Carolina",
    "value": 36,
    "taxonomy": "city_mulaware",
    "code1": null,
    "code2": "NC"
  },
  {
    "name": "Northern Cape",
    "value": 303,
    "taxonomy": "city_mulaware",
    "code1": null,
    "code2": "NC"
  },
  {
    "name": "North Dakota",
    "value": 37,
    "taxonomy": "city_mulaware",
    "code1": null,
    "code2": "ND"
  },
  {
    "name": "Nebraska",
    "value": 30,
    "taxonomy": "city_mulaware",
    "code1": null,
    "code2": "NE"
  },
  {
    "name": "Novgorod Oblast",
    "value": 143,
    "taxonomy": "city_mulaware",
    "code1": null,
    "code2": "NGR"
  },
  {
    "name": "New Hampshire",
    "value": 32,
    "taxonomy": "city_mulaware",
    "code1": null,
    "code2": "NH"
  },
  {
    "name": "Nizhny Novgorod Oblast",
    "value": 142,
    "taxonomy": "city_mulaware",
    "code1": null,
    "code2": "NIZ"
  },
  {
    "name": "New Jersey",
    "value": 33,
    "taxonomy": "city_mulaware",
    "code1": null,
    "code2": "NJ"
  },
  {
    "name": "KwaZulu-Natal",
    "value": 300,
    "taxonomy": "city_mulaware",
    "code1": null,
    "code2": "NL"
  },
  {
    "name": "Nagaland",
    "value": 601,
    "taxonomy": "city_mulaware",
    "code1": null,
    "code2": "NL"
  },
  {
    "name": "Newfoundland and Labrador",
    "value": 537,
    "taxonomy": "city_mulaware",
    "code1": null,
    "code2": "NL"
  },
  {
    "name": "Nuevo León",
    "value": 503,
    "taxonomy": "city_mulaware",
    "code1": null,
    "code2": "NLE"
  },
  {
    "name": "New Mexico",
    "value": 34,
    "taxonomy": "city_mulaware",
    "code1": null,
    "code2": "NM"
  },
  {
    "name": "Novara",
    "value": 367,
    "taxonomy": "city_mulaware",
    "code1": null,
    "code2": "NO"
  },
  {
    "name": "Nova Scotia",
    "value": 539,
    "taxonomy": "city_mulaware",
    "code1": null,
    "code2": "NS"
  },
  {
    "name": "Norte de Santander",
    "value": 664,
    "taxonomy": "city_mulaware",
    "code1": null,
    "code2": "NSA"
  },
  {
    "name": "Nelson",
    "value": 524,
    "taxonomy": "city_mulaware",
    "code1": null,
    "code2": "NSN"
  },
  {
    "name": "Negeri Sembilan",
    "value": 475,
    "taxonomy": "city_mulaware",
    "code1": null,
    "code2": "NSN"
  },
  {
    "name": "New South Wales",
    "value": 2,
    "taxonomy": "city_mulaware",
    "code1": null,
    "code2": "NSW"
  },
  {
    "name": "Nusa Tenggara Timur",
    "value": 634,
    "taxonomy": "city_mulaware",
    "code1": null,
    "code2": "NT"
  },
  {
    "name": "Northern Territory",
    "value": 3,
    "taxonomy": "city_mulaware",
    "code1": null,
    "code2": "NT"
  },
  {
    "name": "Northwest Territories",
    "value": 538,
    "taxonomy": "city_mulaware",
    "code1": null,
    "code2": "NT"
  },
  {
    "name": "Northland",
    "value": 525,
    "taxonomy": "city_mulaware",
    "code1": null,
    "code2": "NTL"
  },
  {
    "name": "Nunavut",
    "value": 540,
    "taxonomy": "city_mulaware",
    "code1": null,
    "code2": "NU"
  },
  {
    "name": "Nuoro",
    "value": 368,
    "taxonomy": "city_mulaware",
    "code1": null,
    "code2": "NU"
  },
  {
    "name": "Nevada",
    "value": 31,
    "taxonomy": "city_mulaware",
    "code1": null,
    "code2": "NV"
  },
  {
    "name": "Novosibirsk Oblast",
    "value": 144,
    "taxonomy": "city_mulaware",
    "code1": null,
    "code2": "NVS"
  },
  {
    "name": "North West",
    "value": 304,
    "taxonomy": "city_mulaware",
    "code1": null,
    "code2": "NW"
  },
  {
    "name": "New York",
    "value": 35,
    "taxonomy": "city_mulaware",
    "code1": null,
    "code2": "NY"
  },
  {
    "name": "Asturias",
    "value": 422,
    "taxonomy": "city_mulaware",
    "code1": null,
    "code2": "O"
  },
  {
    "name": "Oaxaca",
    "value": 504,
    "taxonomy": "city_mulaware",
    "code1": null,
    "code2": "OAX"
  },
  {
    "name": "Ogliastra",
    "value": 369,
    "taxonomy": "city_mulaware",
    "code1": null,
    "code2": "OG"
  },
  {
    "name": "Ohio",
    "value": 38,
    "taxonomy": "city_mulaware",
    "code1": null,
    "code2": "OH"
  },
  {
    "name": "Oklahoma",
    "value": 39,
    "taxonomy": "city_mulaware",
    "code1": null,
    "code2": "OK"
  },
  {
    "name": "Omsk Oblast",
    "value": 145,
    "taxonomy": "city_mulaware",
    "code1": null,
    "code2": "OMS"
  },
  {
    "name": "Ontario",
    "value": 541,
    "taxonomy": "city_mulaware",
    "code1": null,
    "code2": "ON"
  },
  {
    "name": "Ourense (Orense)",
    "value": 453,
    "taxonomy": "city_mulaware",
    "code1": null,
    "code2": "OR"
  },
  {
    "name": "Oregon",
    "value": 40,
    "taxonomy": "city_mulaware",
    "code1": null,
    "code2": "OR"
  },
  {
    "name": "Orissa",
    "value": 602,
    "taxonomy": "city_mulaware",
    "code1": null,
    "code2": "OR"
  },
  {
    "name": "Oristano",
    "value": 371,
    "taxonomy": "city_mulaware",
    "code1": null,
    "code2": "OR"
  },
  {
    "name": "Orenburg Oblast",
    "value": 146,
    "taxonomy": "city_mulaware",
    "code1": null,
    "code2": "ORE"
  },
  {
    "name": "Oryol Oblast",
    "value": 147,
    "taxonomy": "city_mulaware",
    "code1": null,
    "code2": "ORL"
  },
  {
    "name": "Olbia-Tempio",
    "value": 370,
    "taxonomy": "city_mulaware",
    "code1": null,
    "code2": "OT"
  },
  {
    "name": "Otago",
    "value": 526,
    "taxonomy": "city_mulaware",
    "code1": null,
    "code2": "OTA"
  },
  {
    "name": "Formosa",
    "value": 561,
    "taxonomy": "city_mulaware",
    "code1": null,
    "code2": "P"
  },
  {
    "name": "Palencia",
    "value": 454,
    "taxonomy": "city_mulaware",
    "code1": null,
    "code2": "P"
  },
  {
    "name": "Papua",
    "value": 635,
    "taxonomy": "city_mulaware",
    "code1": null,
    "code2": "PA"
  },
  {
    "name": "Pará",
    "value": 84,
    "taxonomy": "city_mulaware",
    "code1": null,
    "code2": "PA"
  },
  {
    "name": "Palermo",
    "value": 373,
    "taxonomy": "city_mulaware",
    "code1": null,
    "code2": "PA"
  },
  {
    "name": "Pennsylvania",
    "value": 47,
    "taxonomy": "city_mulaware",
    "code1": null,
    "code2": "PA"
  },
  {
    "name": "Paraíba",
    "value": 85,
    "taxonomy": "city_mulaware",
    "code1": null,
    "code2": "PB"
  },
  {
    "name": "Punjab",
    "value": 604,
    "taxonomy": "city_mulaware",
    "code1": null,
    "code2": "PB"
  },
  {
    "name": "Papua Barat",
    "value": 636,
    "taxonomy": "city_mulaware",
    "code1": null,
    "code2": "PB"
  },
  {
    "name": "Piacenza",
    "value": 379,
    "taxonomy": "city_mulaware",
    "code1": null,
    "code2": "PC"
  },
  {
    "name": "Padova",
    "value": 372,
    "taxonomy": "city_mulaware",
    "code1": null,
    "code2": "PD"
  },
  {
    "name": "Pernambuco",
    "value": 87,
    "taxonomy": "city_mulaware",
    "code1": null,
    "code2": "PE"
  },
  {
    "name": "Prince Edward Island",
    "value": 542,
    "taxonomy": "city_mulaware",
    "code1": null,
    "code2": "PE"
  },
  {
    "name": "Pescara",
    "value": 378,
    "taxonomy": "city_mulaware",
    "code1": null,
    "code2": "PE"
  },
  {
    "name": "Perm Krai",
    "value": 149,
    "taxonomy": "city_mulaware",
    "code1": null,
    "code2": "PER"
  },
  {
    "name": "Petén",
    "value": 190,
    "taxonomy": "city_mulaware",
    "code1": null,
    "code2": "PET"
  },
  {
    "name": "Perugia",
    "value": 376,
    "taxonomy": "city_mulaware",
    "code1": null,
    "code2": "PG"
  },
  {
    "name": "Pahang",
    "value": 476,
    "taxonomy": "city_mulaware",
    "code1": null,
    "code2": "PHG"
  },
  {
    "name": "Pisa",
    "value": 380,
    "taxonomy": "city_mulaware",
    "code1": null,
    "code2": "PI"
  },
  {
    "name": "Piauí",
    "value": 88,
    "taxonomy": "city_mulaware",
    "code1": null,
    "code2": "PI"
  },
  {
    "name": "Putrajaya",
    "value": 480,
    "taxonomy": "city_mulaware",
    "code1": null,
    "code2": "PJY"
  },
  {
    "name": "Perlis",
    "value": 478,
    "taxonomy": "city_mulaware",
    "code1": null,
    "code2": "PLS"
  },
  {
    "name": "Illes Balears (Islas Baleares)",
    "value": 425,
    "taxonomy": "city_mulaware",
    "code1": null,
    "code2": "PM"
  },
  {
    "name": "Pordenone",
    "value": 382,
    "taxonomy": "city_mulaware",
    "code1": null,
    "code2": "PN"
  },
  {
    "name": "Pulau Pinang",
    "value": 479,
    "taxonomy": "city_mulaware",
    "code1": null,
    "code2": "PNG"
  },
  {
    "name": "Penza Oblast",
    "value": 148,
    "taxonomy": "city_mulaware",
    "code1": null,
    "code2": "PNZ"
  },
  {
    "name": "Prato",
    "value": 384,
    "taxonomy": "city_mulaware",
    "code1": null,
    "code2": "PO"
  },
  {
    "name": "Pontevedra",
    "value": 455,
    "taxonomy": "city_mulaware",
    "code1": null,
    "code2": "PO"
  },
  {
    "name": "Puerto Rico",
    "value": 66,
    "taxonomy": "city_mulaware",
    "code1": null,
    "code2": "PR"
  },
  {
    "name": "Paraná",
    "value": 86,
    "taxonomy": "city_mulaware",
    "code1": null,
    "code2": "PR"
  },
  {
    "name": "Parma",
    "value": 374,
    "taxonomy": "city_mulaware",
    "code1": null,
    "code2": "PR"
  },
  {
    "name": "Primorsky Krai",
    "value": 150,
    "taxonomy": "city_mulaware",
    "code1": null,
    "code2": "PRI"
  },
  {
    "name": "Perak",
    "value": 477,
    "taxonomy": "city_mulaware",
    "code1": null,
    "code2": "PRK"
  },
  {
    "name": "Pskov Oblast",
    "value": 151,
    "taxonomy": "city_mulaware",
    "code1": null,
    "code2": "PSK"
  },
  {
    "name": "Pistoia",
    "value": 381,
    "taxonomy": "city_mulaware",
    "code1": null,
    "code2": "PT"
  },
  {
    "name": "Port Said",
    "value": 288,
    "taxonomy": "city_mulaware",
    "code1": null,
    "code2": "PTS"
  },
  {
    "name": "Pesaro e Urbino",
    "value": 377,
    "taxonomy": "city_mulaware",
    "code1": null,
    "code2": "PU"
  },
  {
    "name": "Puebla",
    "value": 505,
    "taxonomy": "city_mulaware",
    "code1": null,
    "code2": "PUE"
  },
  {
    "name": "Putumayo",
    "value": 673,
    "taxonomy": "city_mulaware",
    "code1": null,
    "code2": "PUT"
  },
  {
    "name": "Pavia",
    "value": 375,
    "taxonomy": "city_mulaware",
    "code1": null,
    "code2": "PV"
  },
  {
    "name": "Palau",
    "value": 65,
    "taxonomy": "city_mulaware",
    "code1": null,
    "code2": "PW"
  },
  {
    "name": "Puducherry",
    "value": 603,
    "taxonomy": "city_mulaware",
    "code1": null,
    "code2": "PY"
  },
  {
    "name": "Potenza",
    "value": 383,
    "taxonomy": "city_mulaware",
    "code1": null,
    "code2": "PZ"
  },
  {
    "name": "Neuquén",
    "value": 567,
    "taxonomy": "city_mulaware",
    "code1": null,
    "code2": "Q"
  },
  {
    "name": "Quebec",
    "value": 543,
    "taxonomy": "city_mulaware",
    "code1": null,
    "code2": "QC"
  },
  {
    "name": "Queensland",
    "value": 4,
    "taxonomy": "city_mulaware",
    "code1": null,
    "code2": "QLD"
  },
  {
    "name": "Quetzaltenango",
    "value": 191,
    "taxonomy": "city_mulaware",
    "code1": null,
    "code2": "QUE"
  },
  {
    "name": "Querétaro",
    "value": 507,
    "taxonomy": "city_mulaware",
    "code1": null,
    "code2": "QUE"
  },
  {
    "name": "Quindio",
    "value": 665,
    "taxonomy": "city_mulaware",
    "code1": null,
    "code2": "QUI"
  },
  {
    "name": "Quiché",
    "value": 192,
    "taxonomy": "city_mulaware",
    "code1": null,
    "code2": "QUI"
  },
  {
    "name": "Río Negro",
    "value": 568,
    "taxonomy": "city_mulaware",
    "code1": null,
    "code2": "R"
  },
  {
    "name": "Ravenna",
    "value": 386,
    "taxonomy": "city_mulaware",
    "code1": null,
    "code2": "RA"
  },
  {
    "name": "Reggio Calabria",
    "value": 387,
    "taxonomy": "city_mulaware",
    "code1": null,
    "code2": "RC"
  },
  {
    "name": "Reggio Emilia",
    "value": 388,
    "taxonomy": "city_mulaware",
    "code1": null,
    "code2": "RE"
  },
  {
    "name": "Retalhuleu",
    "value": 193,
    "taxonomy": "city_mulaware",
    "code1": null,
    "code2": "RET"
  },
  {
    "name": "Ragusa",
    "value": 385,
    "taxonomy": "city_mulaware",
    "code1": null,
    "code2": "RG"
  },
  {
    "name": "Rhode Island",
    "value": 48,
    "taxonomy": "city_mulaware",
    "code1": null,
    "code2": "RI"
  },
  {
    "name": "Rieti",
    "value": 389,
    "taxonomy": "city_mulaware",
    "code1": null,
    "code2": "RI"
  },
  {
    "name": "Riau",
    "value": 637,
    "taxonomy": "city_mulaware",
    "code1": null,
    "code2": "RI"
  },
  {
    "name": "Risaralda",
    "value": 666,
    "taxonomy": "city_mulaware",
    "code1": null,
    "code2": "RIS"
  },
  {
    "name": "Rajasthan",
    "value": 605,
    "taxonomy": "city_mulaware",
    "code1": null,
    "code2": "RJ"
  },
  {
    "name": "Rio de Janeiro",
    "value": 89,
    "taxonomy": "city_mulaware",
    "code1": null,
    "code2": "RJ"
  },
  {
    "name": "Ras al-Khaimah",
    "value": 550,
    "taxonomy": "city_mulaware",
    "code1": null,
    "code2": "RK"
  },
  {
    "name": "Roma",
    "value": 391,
    "taxonomy": "city_mulaware",
    "code1": null,
    "code2": "RM"
  },
  {
    "name": "Rio Grande do Norte",
    "value": 90,
    "taxonomy": "city_mulaware",
    "code1": null,
    "code2": "RN"
  },
  {
    "name": "Rimini",
    "value": 390,
    "taxonomy": "city_mulaware",
    "code1": null,
    "code2": "RN"
  },
  {
    "name": "Rondônia",
    "value": 92,
    "taxonomy": "city_mulaware",
    "code1": null,
    "code2": "RO"
  },
  {
    "name": "Rovigo",
    "value": 392,
    "taxonomy": "city_mulaware",
    "code1": null,
    "code2": "RO"
  },
  {
    "name": "Quintana Roo",
    "value": 506,
    "taxonomy": "city_mulaware",
    "code1": null,
    "code2": "ROO"
  },
  {
    "name": "Rostov Oblast",
    "value": 152,
    "taxonomy": "city_mulaware",
    "code1": null,
    "code2": "ROS"
  },
  {
    "name": "Roraima",
    "value": 93,
    "taxonomy": "city_mulaware",
    "code1": null,
    "code2": "RR"
  },
  {
    "name": "Rio Grande do Sul",
    "value": 91,
    "taxonomy": "city_mulaware",
    "code1": null,
    "code2": "RS"
  },
  {
    "name": "Ryazan Oblast",
    "value": 153,
    "taxonomy": "city_mulaware",
    "code1": null,
    "code2": "RYA"
  },
  {
    "name": "Santa Fe",
    "value": 573,
    "taxonomy": "city_mulaware",
    "code1": null,
    "code2": "S"
  },
  {
    "name": "Cantabria",
    "value": 430,
    "taxonomy": "city_mulaware",
    "code1": null,
    "code2": "S"
  },
  {
    "name": "Sakha Republic (Yakutia)",
    "value": 154,
    "taxonomy": "city_mulaware",
    "code1": null,
    "code2": "SA"
  },
  {
    "name": "South Australia",
    "value": 5,
    "taxonomy": "city_mulaware",
    "code1": null,
    "code2": "SA"
  },
  {
    "name": "Salerno",
    "value": 393,
    "taxonomy": "city_mulaware",
    "code1": null,
    "code2": "SA"
  },
  {
    "name": "Salamanca",
    "value": 456,
    "taxonomy": "city_mulaware",
    "code1": null,
    "code2": "SA"
  },
  {
    "name": "Sulawesi Utara",
    "value": 642,
    "taxonomy": "city_mulaware",
    "code1": null,
    "code2": "SA"
  },
  {
    "name": "Sacatepéquez",
    "value": 194,
    "taxonomy": "city_mulaware",
    "code1": null,
    "code2": "SAC"
  },
  {
    "name": "Sakhalin Oblast",
    "value": 155,
    "taxonomy": "city_mulaware",
    "code1": null,
    "code2": "SAK"
  },
  {
    "name": "Samara Oblast",
    "value": 156,
    "taxonomy": "city_mulaware",
    "code1": null,
    "code2": "SAM"
  },
  {
    "name": "Santander",
    "value": 667,
    "taxonomy": "city_mulaware",
    "code1": null,
    "code2": "SAN"
  },
  {
    "name": "Archipiélago de San Andrés, Providencia y Santa Catalina",
    "value": 674,
    "taxonomy": "city_mulaware",
    "code1": null,
    "code2": "SAP"
  },
  {
    "name": "Saratov Oblast",
    "value": 158,
    "taxonomy": "city_mulaware",
    "code1": null,
    "code2": "SAR"
  },
  {
    "name": "Sumatra Barat",
    "value": 643,
    "taxonomy": "city_mulaware",
    "code1": null,
    "code2": "SB"
  },
  {
    "name": "Sabah",
    "value": 481,
    "taxonomy": "city_mulaware",
    "code1": null,
    "code2": "SBH"
  },
  {
    "name": "Santa Catarina",
    "value": 94,
    "taxonomy": "city_mulaware",
    "code1": null,
    "code2": "SC"
  },
  {
    "name": "South Carolina",
    "value": 49,
    "taxonomy": "city_mulaware",
    "code1": null,
    "code2": "SC"
  },
  {
    "name": "South Dakota",
    "value": 50,
    "taxonomy": "city_mulaware",
    "code1": null,
    "code2": "SD"
  },
  {
    "name": "Sevilla",
    "value": 459,
    "taxonomy": "city_mulaware",
    "code1": null,
    "code2": "SE"
  },
  {
    "name": "Republic of North Ossetia–Alania",
    "value": 159,
    "taxonomy": "city_mulaware",
    "code1": null,
    "code2": "SE"
  },
  {
    "name": "Sergipe",
    "value": 96,
    "taxonomy": "city_mulaware",
    "code1": null,
    "code2": "SE"
  },
  {
    "name": "Segovia",
    "value": 458,
    "taxonomy": "city_mulaware",
    "code1": null,
    "code2": "SG"
  },
  {
    "name": "Sulawesi Tenggara",
    "value": 641,
    "taxonomy": "city_mulaware",
    "code1": null,
    "code2": "SG"
  },
  {
    "name": "Selangor",
    "value": 483,
    "taxonomy": "city_mulaware",
    "code1": null,
    "code2": "SGR"
  },
  {
    "name": "Sharjah",
    "value": 551,
    "taxonomy": "city_mulaware",
    "code1": null,
    "code2": "SH"
  },
  {
    "name": "Sohag",
    "value": 296,
    "taxonomy": "city_mulaware",
    "code1": null,
    "code2": "SHG"
  },
  {
    "name": "Al Sharqia",
    "value": 282,
    "taxonomy": "city_mulaware",
    "code1": null,
    "code2": "SHR"
  },
  {
    "name": "Siena",
    "value": 396,
    "taxonomy": "city_mulaware",
    "code1": null,
    "code2": "SI"
  },
  {
    "name": "North Sinai",
    "value": 295,
    "taxonomy": "city_mulaware",
    "code1": null,
    "code2": "SIN"
  },
  {
    "name": "Sinaloa",
    "value": 508,
    "taxonomy": "city_mulaware",
    "code1": null,
    "code2": "SIN"
  },
  {
    "name": "Saskatchewan",
    "value": 544,
    "taxonomy": "city_mulaware",
    "code1": null,
    "code2": "SK"
  },
  {
    "name": "Sikkim",
    "value": 606,
    "taxonomy": "city_mulaware",
    "code1": null,
    "code2": "SK"
  },
  {
    "name": "San Luis Potosí",
    "value": 509,
    "taxonomy": "city_mulaware",
    "code1": null,
    "code2": "SLP"
  },
  {
    "name": "San Marcos",
    "value": 195,
    "taxonomy": "city_mulaware",
    "code1": null,
    "code2": "SMA"
  },
  {
    "name": "Smolensk Oblast",
    "value": 160,
    "taxonomy": "city_mulaware",
    "code1": null,
    "code2": "SMO"
  },
  {
    "name": "Sulawesi Selatan",
    "value": 639,
    "taxonomy": "city_mulaware",
    "code1": null,
    "code2": "SN"
  },
  {
    "name": "Soria",
    "value": 460,
    "taxonomy": "city_mulaware",
    "code1": null,
    "code2": "SO"
  },
  {
    "name": "Sondrio",
    "value": 398,
    "taxonomy": "city_mulaware",
    "code1": null,
    "code2": "SO"
  },
  {
    "name": "Sololá",
    "value": 197,
    "taxonomy": "city_mulaware",
    "code1": null,
    "code2": "SOL"
  },
  {
    "name": "Sonora",
    "value": 510,
    "taxonomy": "city_mulaware",
    "code1": null,
    "code2": "SON"
  },
  {
    "name": "São Paulo",
    "value": 95,
    "taxonomy": "city_mulaware",
    "code1": null,
    "code2": "SP"
  },
  {
    "name": "La Spezia",
    "value": 349,
    "taxonomy": "city_mulaware",
    "code1": null,
    "code2": "SP"
  },
  {
    "name": "Saint Petersburg",
    "value": 157,
    "taxonomy": "city_mulaware",
    "code1": null,
    "code2": "SPE"
  },
  {
    "name": "Sulawesi Barat",
    "value": 638,
    "taxonomy": "city_mulaware",
    "code1": null,
    "code2": "SR"
  },
  {
    "name": "Siracusa",
    "value": 397,
    "taxonomy": "city_mulaware",
    "code1": null,
    "code2": "SR"
  },
  {
    "name": "Santa Rosa",
    "value": 196,
    "taxonomy": "city_mulaware",
    "code1": null,
    "code2": "SRO"
  },
  {
    "name": "Sumatra Selatan",
    "value": 644,
    "taxonomy": "city_mulaware",
    "code1": null,
    "code2": "SS"
  },
  {
    "name": "Sassari",
    "value": 394,
    "taxonomy": "city_mulaware",
    "code1": null,
    "code2": "SS"
  },
  {
    "name": "Gipuzkoa (Guipúzcoa)",
    "value": 439,
    "taxonomy": "city_mulaware",
    "code1": null,
    "code2": "SS"
  },
  {
    "name": "Sulawesi Tengah",
    "value": 640,
    "taxonomy": "city_mulaware",
    "code1": null,
    "code2": "ST"
  },
  {
    "name": "Stavropol Krai",
    "value": 161,
    "taxonomy": "city_mulaware",
    "code1": null,
    "code2": "STA"
  },
  {
    "name": "Southland",
    "value": 527,
    "taxonomy": "city_mulaware",
    "code1": null,
    "code2": "STL"
  },
  {
    "name": "6th of October",
    "value": 283,
    "taxonomy": "city_mulaware",
    "code1": null,
    "code2": "SU"
  },
  {
    "name": "Sumatra Utara",
    "value": 645,
    "taxonomy": "city_mulaware",
    "code1": null,
    "code2": "SU"
  },
  {
    "name": "Sud Sardegna",
    "value": 399,
    "taxonomy": "city_mulaware",
    "code1": null,
    "code2": "SU"
  },
  {
    "name": "Suchitepéquez",
    "value": 198,
    "taxonomy": "city_mulaware",
    "code1": null,
    "code2": "SUC"
  },
  {
    "name": "Sucre",
    "value": 668,
    "taxonomy": "city_mulaware",
    "code1": null,
    "code2": "SUC"
  },
  {
    "name": "Suez",
    "value": 284,
    "taxonomy": "city_mulaware",
    "code1": null,
    "code2": "SUZ"
  },
  {
    "name": "Savona",
    "value": 395,
    "taxonomy": "city_mulaware",
    "code1": null,
    "code2": "SV"
  },
  {
    "name": "Sverdlovsk Oblast",
    "value": 162,
    "taxonomy": "city_mulaware",
    "code1": null,
    "code2": "SVE"
  },
  {
    "name": "Sarawak",
    "value": 482,
    "taxonomy": "city_mulaware",
    "code1": null,
    "code2": "SWK"
  },
  {
    "name": "Tarragona",
    "value": 461,
    "taxonomy": "city_mulaware",
    "code1": null,
    "code2": "T"
  },
  {
    "name": "Tucumán",
    "value": 576,
    "taxonomy": "city_mulaware",
    "code1": null,
    "code2": "T"
  },
  {
    "name": "Taranto",
    "value": 400,
    "taxonomy": "city_mulaware",
    "code1": null,
    "code2": "TA"
  },
  {
    "name": "Republic of Tatarstan",
    "value": 164,
    "taxonomy": "city_mulaware",
    "code1": null,
    "code2": "TA"
  },
  {
    "name": "Tabasco",
    "value": 511,
    "taxonomy": "city_mulaware",
    "code1": null,
    "code2": "TAB"
  },
  {
    "name": "Tambov Oblast",
    "value": 163,
    "taxonomy": "city_mulaware",
    "code1": null,
    "code2": "TAM"
  },
  {
    "name": "Tamaulipas",
    "value": 513,
    "taxonomy": "city_mulaware",
    "code1": null,
    "code2": "TAM"
  },
  {
    "name": "Tasmania",
    "value": 6,
    "taxonomy": "city_mulaware",
    "code1": null,
    "code2": "TAS"
  },
  {
    "name": "Tasman",
    "value": 529,
    "taxonomy": "city_mulaware",
    "code1": null,
    "code2": "TAS"
  },
  {
    "name": "Teruel",
    "value": 462,
    "taxonomy": "city_mulaware",
    "code1": null,
    "code2": "TE"
  },
  {
    "name": "Teramo",
    "value": 401,
    "taxonomy": "city_mulaware",
    "code1": null,
    "code2": "TE"
  },
  {
    "name": "Santa Cruz de Tenerife",
    "value": 457,
    "taxonomy": "city_mulaware",
    "code1": null,
    "code2": "TF"
  },
  {
    "name": "Taranaki",
    "value": 528,
    "taxonomy": "city_mulaware",
    "code1": null,
    "code2": "TKI"
  },
  {
    "name": "Tlaxcala",
    "value": 512,
    "taxonomy": "city_mulaware",
    "code1": null,
    "code2": "TLA"
  },
  {
    "name": "Tamil Nadu",
    "value": 607,
    "taxonomy": "city_mulaware",
    "code1": null,
    "code2": "TN"
  },
  {
    "name": "Trento",
    "value": 405,
    "taxonomy": "city_mulaware",
    "code1": null,
    "code2": "TN"
  },
  {
    "name": "Tennessee",
    "value": 51,
    "taxonomy": "city_mulaware",
    "code1": null,
    "code2": "TN"
  },
  {
    "name": "Toledo",
    "value": 463,
    "taxonomy": "city_mulaware",
    "code1": null,
    "code2": "TO"
  },
  {
    "name": "Tocantins",
    "value": 97,
    "taxonomy": "city_mulaware",
    "code1": null,
    "code2": "TO"
  },
  {
    "name": "Torino",
    "value": 403,
    "taxonomy": "city_mulaware",
    "code1": null,
    "code2": "TO"
  },
  {
    "name": "Tolima",
    "value": 669,
    "taxonomy": "city_mulaware",
    "code1": null,
    "code2": "TOL"
  },
  {
    "name": "Tomsk Oblast",
    "value": 165,
    "taxonomy": "city_mulaware",
    "code1": null,
    "code2": "TOM"
  },
  {
    "name": "Totonicapán",
    "value": 199,
    "taxonomy": "city_mulaware",
    "code1": null,
    "code2": "TOT"
  },
  {
    "name": "Trapani",
    "value": 404,
    "taxonomy": "city_mulaware",
    "code1": null,
    "code2": "TP"
  },
  {
    "name": "Tripura",
    "value": 609,
    "taxonomy": "city_mulaware",
    "code1": null,
    "code2": "TR"
  },
  {
    "name": "Terni",
    "value": 402,
    "taxonomy": "city_mulaware",
    "code1": null,
    "code2": "TR"
  },
  {
    "name": "Terengganu",
    "value": 484,
    "taxonomy": "city_mulaware",
    "code1": null,
    "code2": "TRG"
  },
  {
    "name": "Trieste",
    "value": 407,
    "taxonomy": "city_mulaware",
    "code1": null,
    "code2": "TS"
  },
  {
    "name": "Telangana",
    "value": 608,
    "taxonomy": "city_mulaware",
    "code1": null,
    "code2": "TS"
  },
  {
    "name": "Tula Oblast",
    "value": 166,
    "taxonomy": "city_mulaware",
    "code1": null,
    "code2": "TUL"
  },
  {
    "name": "Treviso",
    "value": 406,
    "taxonomy": "city_mulaware",
    "code1": null,
    "code2": "TV"
  },
  {
    "name": "Tver Oblast",
    "value": 167,
    "taxonomy": "city_mulaware",
    "code1": null,
    "code2": "TVE"
  },
  {
    "name": "Texas",
    "value": 52,
    "taxonomy": "city_mulaware",
    "code1": null,
    "code2": "TX"
  },
  {
    "name": "Tyva Republic",
    "value": 169,
    "taxonomy": "city_mulaware",
    "code1": null,
    "code2": "TY"
  },
  {
    "name": "Tyumen Oblast",
    "value": 168,
    "taxonomy": "city_mulaware",
    "code1": null,
    "code2": "TYU"
  },
  {
    "name": "Chubut",
    "value": 557,
    "taxonomy": "city_mulaware",
    "code1": null,
    "code2": "U"
  },
  {
    "name": "Udine",
    "value": 408,
    "taxonomy": "city_mulaware",
    "code1": null,
    "code2": "UD"
  },
  {
    "name": "Udmurtia",
    "value": 170,
    "taxonomy": "city_mulaware",
    "code1": null,
    "code2": "UD"
  },
  {
    "name": "Uttarakhand",
    "value": 611,
    "taxonomy": "city_mulaware",
    "code1": null,
    "code2": "UK"
  },
  {
    "name": "Ulyanovsk Oblast",
    "value": 171,
    "taxonomy": "city_mulaware",
    "code1": null,
    "code2": "ULY"
  },
  {
    "name": "Uttar Pradesh",
    "value": 610,
    "taxonomy": "city_mulaware",
    "code1": null,
    "code2": "UP"
  },
  {
    "name": "Umm al-Quwain",
    "value": 552,
    "taxonomy": "city_mulaware",
    "code1": null,
    "code2": "UQ"
  },
  {
    "name": "Utah",
    "value": 53,
    "taxonomy": "city_mulaware",
    "code1": null,
    "code2": "UT"
  },
  {
    "name": "Tierra del Fuego",
    "value": 575,
    "taxonomy": "city_mulaware",
    "code1": null,
    "code2": "V"
  },
  {
    "name": "València (Valencia)",
    "value": 464,
    "taxonomy": "city_mulaware",
    "code1": null,
    "code2": "V"
  },
  {
    "name": "Varese",
    "value": 409,
    "taxonomy": "city_mulaware",
    "code1": null,
    "code2": "VA"
  },
  {
    "name": "Valladolid",
    "value": 465,
    "taxonomy": "city_mulaware",
    "code1": null,
    "code2": "VA"
  },
  {
    "name": "Virginia",
    "value": 55,
    "taxonomy": "city_mulaware",
    "code1": null,
    "code2": "VA"
  },
  {
    "name": "Valle del Cauca",
    "value": 670,
    "taxonomy": "city_mulaware",
    "code1": null,
    "code2": "VAC"
  },
  {
    "name": "Vaupés",
    "value": 678,
    "taxonomy": "city_mulaware",
    "code1": null,
    "code2": "VAU"
  },
  {
    "name": "Verbano-Cusio-Ossola",
    "value": 411,
    "taxonomy": "city_mulaware",
    "code1": null,
    "code2": "VB"
  },
  {
    "name": "Vercelli",
    "value": 412,
    "taxonomy": "city_mulaware",
    "code1": null,
    "code2": "VC"
  },
  {
    "name": "Venezia",
    "value": 410,
    "taxonomy": "city_mulaware",
    "code1": null,
    "code2": "VE"
  },
  {
    "name": "Veracruz",
    "value": 514,
    "taxonomy": "city_mulaware",
    "code1": null,
    "code2": "VER"
  },
  {
    "name": "Volgograd Oblast",
    "value": 173,
    "taxonomy": "city_mulaware",
    "code1": null,
    "code2": "VGG"
  },
  {
    "name": "Vicenza",
    "value": 415,
    "taxonomy": "city_mulaware",
    "code1": null,
    "code2": "VI"
  },
  {
    "name": "Araba/Álava",
    "value": 418,
    "taxonomy": "city_mulaware",
    "code1": null,
    "code2": "VI"
  },
  {
    "name": "Virgin Islands",
    "value": 67,
    "taxonomy": "city_mulaware",
    "code1": null,
    "code2": "VI"
  },
  {
    "name": "Victoria",
    "value": 7,
    "taxonomy": "city_mulaware",
    "code1": null,
    "code2": "VIC"
  },
  {
    "name": "Vichada",
    "value": 679,
    "taxonomy": "city_mulaware",
    "code1": null,
    "code2": "VID"
  },
  {
    "name": "Vladimir Oblast",
    "value": 172,
    "taxonomy": "city_mulaware",
    "code1": null,
    "code2": "VLA"
  },
  {
    "name": "Vologda Oblast",
    "value": 174,
    "taxonomy": "city_mulaware",
    "code1": null,
    "code2": "VLG"
  },
  {
    "name": "Voronezh Oblast",
    "value": 175,
    "taxonomy": "city_mulaware",
    "code1": null,
    "code2": "VOR"
  },
  {
    "name": "Verona",
    "value": 413,
    "taxonomy": "city_mulaware",
    "code1": null,
    "code2": "VR"
  },
  {
    "name": "Medio Campidano",
    "value": 361,
    "taxonomy": "city_mulaware",
    "code1": null,
    "code2": "VS"
  },
  {
    "name": "Viterbo",
    "value": 416,
    "taxonomy": "city_mulaware",
    "code1": null,
    "code2": "VT"
  },
  {
    "name": "Vermont",
    "value": 54,
    "taxonomy": "city_mulaware",
    "code1": null,
    "code2": "VT"
  },
  {
    "name": "Vibo Valentia",
    "value": 414,
    "taxonomy": "city_mulaware",
    "code1": null,
    "code2": "VV"
  },
  {
    "name": "Corrientes",
    "value": 559,
    "taxonomy": "city_mulaware",
    "code1": null,
    "code2": "W"
  },
  {
    "name": "Washington",
    "value": 56,
    "taxonomy": "city_mulaware",
    "code1": null,
    "code2": "WA"
  },
  {
    "name": "Western Australia",
    "value": 8,
    "taxonomy": "city_mulaware",
    "code1": null,
    "code2": "WA"
  },
  {
    "name": "New Valley",
    "value": 281,
    "taxonomy": "city_mulaware",
    "code1": null,
    "code2": "WAD"
  },
  {
    "name": "West Bengal",
    "value": 612,
    "taxonomy": "city_mulaware",
    "code1": null,
    "code2": "WB"
  },
  {
    "name": "Western Cape",
    "value": 305,
    "taxonomy": "city_mulaware",
    "code1": null,
    "code2": "WC"
  },
  {
    "name": "Wellington",
    "value": 531,
    "taxonomy": "city_mulaware",
    "code1": null,
    "code2": "WGN"
  },
  {
    "name": "Wisconsin",
    "value": 58,
    "taxonomy": "city_mulaware",
    "code1": null,
    "code2": "WI"
  },
  {
    "name": "Waikato",
    "value": 530,
    "taxonomy": "city_mulaware",
    "code1": null,
    "code2": "WKO"
  },
  {
    "name": "West Coast",
    "value": 532,
    "taxonomy": "city_mulaware",
    "code1": null,
    "code2": "WTC"
  },
  {
    "name": "West Virginia",
    "value": 57,
    "taxonomy": "city_mulaware",
    "code1": null,
    "code2": "WV"
  },
  {
    "name": "Wyoming",
    "value": 59,
    "taxonomy": "city_mulaware",
    "code1": null,
    "code2": "WY"
  },
  {
    "name": "Córdoba",
    "value": 558,
    "taxonomy": "city_mulaware",
    "code1": null,
    "code2": "X"
  },
  {
    "name": "Jujuy",
    "value": 562,
    "taxonomy": "city_mulaware",
    "code1": null,
    "code2": "Y"
  },
  {
    "name": "Yamalo-Nenets Autonomous Okrug",
    "value": 176,
    "taxonomy": "city_mulaware",
    "code1": null,
    "code2": "YAN"
  },
  {
    "name": "Yaroslavl Oblast",
    "value": 177,
    "taxonomy": "city_mulaware",
    "code1": null,
    "code2": "YAR"
  },
  {
    "name": "Jewish Autonomous Oblast",
    "value": 178,
    "taxonomy": "city_mulaware",
    "code1": null,
    "code2": "YEV"
  },
  {
    "name": "Yogyakarta",
    "value": 646,
    "taxonomy": "city_mulaware",
    "code1": null,
    "code2": "YO"
  },
  {
    "name": "Yukon",
    "value": 545,
    "taxonomy": "city_mulaware",
    "code1": null,
    "code2": "YT"
  },
  {
    "name": "Yucatán",
    "value": 515,
    "taxonomy": "city_mulaware",
    "code1": null,
    "code2": "YUC"
  },
  {
    "name": "Zaragoza",
    "value": 468,
    "taxonomy": "city_mulaware",
    "code1": null,
    "code2": "Z"
  },
  {
    "name": "Santa Cruz",
    "value": 572,
    "taxonomy": "city_mulaware",
    "code1": null,
    "code2": "Z"
  },
  {
    "name": "Zamora",
    "value": 467,
    "taxonomy": "city_mulaware",
    "code1": null,
    "code2": "ZA"
  },
  {
    "name": "Zacatecas",
    "value": 516,
    "taxonomy": "city_mulaware",
    "code1": null,
    "code2": "ZAC"
  },
  {
    "name": "Zacapa",
    "value": 200,
    "taxonomy": "city_mulaware",
    "code1": null,
    "code2": "ZAC"
  }
]